{
"meta":{"test_sets":[],"test_metrics":[],"learn_metrics":[{"best_value":"Min","name":"RMSE"}],"launch_mode":"Train","parameters":"","iteration_count":1000,"learn_sets":["learn"],"name":"experiment"},
"iterations":[
{"learn":[14.61268541],"iteration":0,"passed_time":0.1642382216,"remaining_time":164.0739833},
{"learn":[14.23196558],"iteration":1,"passed_time":0.1651289322,"remaining_time":82.39933716},
{"learn":[13.86674177],"iteration":2,"passed_time":0.1659935597,"remaining_time":55.16519302},
{"learn":[13.49946468],"iteration":3,"passed_time":0.1667486732,"remaining_time":41.52041962},
{"learn":[13.16661202],"iteration":4,"passed_time":0.1675418945,"remaining_time":33.34083701},
{"learn":[12.85632158],"iteration":5,"passed_time":0.1681776139,"remaining_time":27.86142471},
{"learn":[12.56784336],"iteration":6,"passed_time":0.1687685017,"remaining_time":23.94101745},
{"learn":[12.31617801],"iteration":7,"passed_time":0.1693646502,"remaining_time":21.00121663},
{"learn":[12.01509946],"iteration":8,"passed_time":0.1699488142,"remaining_time":18.71325277},
{"learn":[11.71512571],"iteration":9,"passed_time":0.1705269459,"remaining_time":16.88216765},
{"learn":[11.43264457],"iteration":10,"passed_time":0.1711054183,"remaining_time":15.38393261},
{"learn":[11.17973129],"iteration":11,"passed_time":0.1717039417,"remaining_time":14.13695787},
{"learn":[10.93746433],"iteration":12,"passed_time":0.1722854202,"remaining_time":13.08043921},
{"learn":[10.69387075],"iteration":13,"passed_time":0.1728620188,"remaining_time":12.17442504},
{"learn":[10.4615922],"iteration":14,"passed_time":0.173448698,"remaining_time":11.38979783},
{"learn":[10.2299235],"iteration":15,"passed_time":0.1740575425,"remaining_time":10.70453886},
{"learn":[10.01419731],"iteration":16,"passed_time":0.1746410952,"remaining_time":10.09836451},
{"learn":[9.795856918],"iteration":17,"passed_time":0.1752076232,"remaining_time":9.558549222},
{"learn":[9.60040151],"iteration":18,"passed_time":0.1758110466,"remaining_time":9.077401932},
{"learn":[9.418664989],"iteration":19,"passed_time":0.1763782059,"remaining_time":8.642532088},
{"learn":[9.249278645],"iteration":20,"passed_time":0.1769527903,"remaining_time":8.249370558},
{"learn":[9.090113396],"iteration":21,"passed_time":0.1775456521,"remaining_time":7.892711262},
{"learn":[8.909548708],"iteration":22,"passed_time":0.1781274313,"remaining_time":7.566543494},
{"learn":[8.740140208],"iteration":23,"passed_time":0.1787137998,"remaining_time":7.267694525},
{"learn":[8.59377682],"iteration":24,"passed_time":0.1793033248,"remaining_time":6.992829667},
{"learn":[8.453885414],"iteration":25,"passed_time":0.1800289379,"remaining_time":6.744160983},
{"learn":[8.317732234],"iteration":26,"passed_time":0.1806774735,"remaining_time":6.511080806},
{"learn":[8.180896085],"iteration":27,"passed_time":0.1813089342,"remaining_time":6.294010146},
{"learn":[8.053220863],"iteration":28,"passed_time":0.1818809935,"remaining_time":6.089877404},
{"learn":[7.924234474],"iteration":29,"passed_time":0.1824524816,"remaining_time":5.899296906},
{"learn":[7.818879511],"iteration":30,"passed_time":0.1830263947,"remaining_time":5.721050854},
{"learn":[7.719346395],"iteration":31,"passed_time":0.1836115007,"remaining_time":5.554247895},
{"learn":[7.624163594],"iteration":32,"passed_time":0.1841851231,"remaining_time":5.397182245},
{"learn":[7.524952543],"iteration":33,"passed_time":0.1847567315,"remaining_time":5.249264783},
{"learn":[7.424464745],"iteration":34,"passed_time":0.1853306847,"remaining_time":5.109831734},
{"learn":[7.327482321],"iteration":35,"passed_time":0.1858807991,"remaining_time":4.977474731},
{"learn":[7.238666841],"iteration":36,"passed_time":0.1865829646,"remaining_time":4.856199862},
{"learn":[7.158842395],"iteration":37,"passed_time":0.1873628587,"remaining_time":4.743238685},
{"learn":[7.074348246],"iteration":38,"passed_time":0.1880778501,"remaining_time":4.634431127},
{"learn":[6.992269093],"iteration":39,"passed_time":0.1888200369,"remaining_time":4.531680885},
{"learn":[6.925219745],"iteration":40,"passed_time":0.1895279138,"remaining_time":4.433104129},
{"learn":[6.86013671],"iteration":41,"passed_time":0.1902502502,"remaining_time":4.339517612},
{"learn":[6.786739622],"iteration":42,"passed_time":0.1908660592,"remaining_time":4.247879503},
{"learn":[6.73057926],"iteration":43,"passed_time":0.1914909064,"remaining_time":4.160575148},
{"learn":[6.666356486],"iteration":44,"passed_time":0.1920933876,"remaining_time":4.076648558},
{"learn":[6.606182832],"iteration":45,"passed_time":0.1927611124,"remaining_time":3.997697853},
{"learn":[6.547854615],"iteration":46,"passed_time":0.1933927935,"remaining_time":3.921347495},
{"learn":[6.49240675],"iteration":47,"passed_time":0.1940867322,"remaining_time":3.849386856},
{"learn":[6.431317261],"iteration":48,"passed_time":0.1948360538,"remaining_time":3.781409943},
{"learn":[6.377586395],"iteration":49,"passed_time":0.1955269761,"remaining_time":3.715012545},
{"learn":[6.327558015],"iteration":50,"passed_time":0.1961113505,"remaining_time":3.649209248},
{"learn":[6.282040317],"iteration":51,"passed_time":0.1966784898,"remaining_time":3.585600159},
{"learn":[6.237655841],"iteration":52,"passed_time":0.1972376827,"remaining_time":3.524228029},
{"learn":[6.192792003],"iteration":53,"passed_time":0.197821466,"remaining_time":3.465539015},
{"learn":[6.150579347],"iteration":54,"passed_time":0.1984103497,"remaining_time":3.409050553},
{"learn":[6.115693845],"iteration":55,"passed_time":0.1989857257,"remaining_time":3.354330805},
{"learn":[6.078780782],"iteration":56,"passed_time":0.1995578552,"remaining_time":3.301457147},
{"learn":[6.045146957],"iteration":57,"passed_time":0.2001170982,"remaining_time":3.250177699},
{"learn":[6.008080327],"iteration":58,"passed_time":0.2006927749,"remaining_time":3.200879681},
{"learn":[5.977575734],"iteration":59,"passed_time":0.2012551644,"remaining_time":3.152997576},
{"learn":[5.948036502],"iteration":60,"passed_time":0.2018462426,"remaining_time":3.107108554},
{"learn":[5.914888282],"iteration":61,"passed_time":0.2024280418,"remaining_time":3.062540374},
{"learn":[5.884957796],"iteration":62,"passed_time":0.2029989587,"remaining_time":3.019206736},
{"learn":[5.849539885],"iteration":63,"passed_time":0.2035979531,"remaining_time":2.977620064},
{"learn":[5.821387627],"iteration":64,"passed_time":0.2041898629,"remaining_time":2.937192644},
{"learn":[5.797012279],"iteration":65,"passed_time":0.2047607699,"remaining_time":2.897675137},
{"learn":[5.768685095],"iteration":66,"passed_time":0.2053256144,"remaining_time":2.859235795},
{"learn":[5.755484587],"iteration":67,"passed_time":0.2056268501,"remaining_time":2.818297416},
{"learn":[5.731887055],"iteration":68,"passed_time":0.2062015448,"remaining_time":2.782226641},
{"learn":[5.707148487],"iteration":69,"passed_time":0.2067701871,"remaining_time":2.747089629},
{"learn":[5.685365039],"iteration":70,"passed_time":0.207356245,"remaining_time":2.713154248},
{"learn":[5.663541834],"iteration":71,"passed_time":0.2079337554,"remaining_time":2.68003507},
{"learn":[5.638108797],"iteration":72,"passed_time":0.2084941609,"remaining_time":2.647590235},
{"learn":[5.619204893],"iteration":73,"passed_time":0.2091207419,"remaining_time":2.61683523},
{"learn":[5.598472793],"iteration":74,"passed_time":0.2097336246,"remaining_time":2.586714704},
{"learn":[5.577007075],"iteration":75,"passed_time":0.2103479202,"remaining_time":2.557387872},
{"learn":[5.562637084],"iteration":76,"passed_time":0.2109359121,"remaining_time":2.528491517},
{"learn":[5.54729991],"iteration":77,"passed_time":0.2115148855,"remaining_time":2.500214416},
{"learn":[5.530737623],"iteration":78,"passed_time":0.2121134289,"remaining_time":2.472866684},
{"learn":[5.513704873],"iteration":79,"passed_time":0.2127012003,"remaining_time":2.446063804},
{"learn":[5.501575529],"iteration":80,"passed_time":0.213289603,"remaining_time":2.419915372},
{"learn":[5.484080734],"iteration":81,"passed_time":0.2138553193,"remaining_time":2.39413638},
{"learn":[5.472178894],"iteration":82,"passed_time":0.2144430807,"remaining_time":2.369208494},
{"learn":[5.458923342],"iteration":83,"passed_time":0.2150112621,"remaining_time":2.34464662},
{"learn":[5.451382371],"iteration":84,"passed_time":0.2153988242,"remaining_time":2.31870499},
{"learn":[5.441410748],"iteration":85,"passed_time":0.2159825273,"remaining_time":2.295442209},
{"learn":[5.434047468],"iteration":86,"passed_time":0.2163610811,"remaining_time":2.270547897},
{"learn":[5.422107497],"iteration":87,"passed_time":0.2169550451,"remaining_time":2.248443195},
{"learn":[5.40731265],"iteration":88,"passed_time":0.2175183766,"remaining_time":2.226508327},
{"learn":[5.396360181],"iteration":89,"passed_time":0.2181185834,"remaining_time":2.205421232},
{"learn":[5.383793239],"iteration":90,"passed_time":0.2187019959,"remaining_time":2.18461664},
{"learn":[5.369605034],"iteration":91,"passed_time":0.2192869415,"remaining_time":2.164266771},
{"learn":[5.357467333],"iteration":92,"passed_time":0.2198594617,"remaining_time":2.144220772},
{"learn":[5.341109968],"iteration":93,"passed_time":0.2204409202,"remaining_time":2.124675252},
{"learn":[5.330529276],"iteration":94,"passed_time":0.2210120075,"remaining_time":2.105430177},
{"learn":[5.319862075],"iteration":95,"passed_time":0.2215881852,"remaining_time":2.086622078},
{"learn":[5.313052243],"iteration":96,"passed_time":0.2221410252,"remaining_time":2.067972637},
{"learn":[5.299677207],"iteration":97,"passed_time":0.2227180647,"remaining_time":2.049915249},
{"learn":[5.287546698],"iteration":98,"passed_time":0.2232835505,"remaining_time":2.032105849},
{"learn":[5.279803754],"iteration":99,"passed_time":0.2238681655,"remaining_time":2.014813489},
{"learn":[5.272254612],"iteration":100,"passed_time":0.2246875804,"remaining_time":1.999941928},
{"learn":[5.268813888],"iteration":101,"passed_time":0.2251458319,"remaining_time":1.982166246},
{"learn":[5.258113767],"iteration":102,"passed_time":0.225901832,"remaining_time":1.967319838},
{"learn":[5.251018576],"iteration":103,"passed_time":0.2265529429,"remaining_time":1.951840739},
{"learn":[5.24171237],"iteration":104,"passed_time":0.2271464159,"remaining_time":1.936152783},
{"learn":[5.233984943],"iteration":105,"passed_time":0.2277235656,"remaining_time":1.920611959},
{"learn":[5.226240449],"iteration":106,"passed_time":0.2283250952,"remaining_time":1.905554299},
{"learn":[5.220541644],"iteration":107,"passed_time":0.2288748388,"remaining_time":1.890336632},
{"learn":[5.211712096],"iteration":108,"passed_time":0.2294496337,"remaining_time":1.875592877},
{"learn":[5.203388597],"iteration":109,"passed_time":0.2300192179,"remaining_time":1.861064581},
{"learn":[5.196026544],"iteration":110,"passed_time":0.2305819381,"remaining_time":1.84673282},
{"learn":[5.188716772],"iteration":111,"passed_time":0.2311479751,"remaining_time":1.832673231},
{"learn":[5.182163132],"iteration":112,"passed_time":0.2317463782,"remaining_time":1.819106526},
{"learn":[5.17764747],"iteration":113,"passed_time":0.232320612,"remaining_time":1.805579493},
{"learn":[5.170548056],"iteration":114,"passed_time":0.232905287,"remaining_time":1.792358078},
{"learn":[5.165901827],"iteration":115,"passed_time":0.2333666901,"remaining_time":1.778415121},
{"learn":[5.160333668],"iteration":116,"passed_time":0.233969352,"remaining_time":1.765768699},
{"learn":[5.148953243],"iteration":117,"passed_time":0.2345793789,"remaining_time":1.753381459},
{"learn":[5.144729126],"iteration":118,"passed_time":0.235064781,"remaining_time":1.740269513},
{"learn":[5.139939946],"iteration":119,"passed_time":0.2356407182,"remaining_time":1.728031934},
{"learn":[5.132898872],"iteration":120,"passed_time":0.2362235495,"remaining_time":1.71603719},
{"learn":[5.129073077],"iteration":121,"passed_time":0.2367864601,"remaining_time":1.704086164},
{"learn":[5.127123916],"iteration":122,"passed_time":0.2370913533,"remaining_time":1.690480625},
{"learn":[5.121282057],"iteration":123,"passed_time":0.2376555766,"remaining_time":1.678921654},
{"learn":[5.114489821],"iteration":124,"passed_time":0.2382181364,"remaining_time":1.667526955},
{"learn":[5.107777291],"iteration":125,"passed_time":0.2388031121,"remaining_time":1.656459683},
{"learn":[5.103518754],"iteration":126,"passed_time":0.2395124723,"remaining_time":1.646412507},
{"learn":[5.101133351],"iteration":127,"passed_time":0.2398896032,"remaining_time":1.634247922},
{"learn":[5.096462705],"iteration":128,"passed_time":0.2405640317,"remaining_time":1.624273423},
{"learn":[5.08562082],"iteration":129,"passed_time":0.2411559416,"remaining_time":1.613889763},
{"learn":[5.080483682],"iteration":130,"passed_time":0.2417734237,"remaining_time":1.60382523},
{"learn":[5.07437499],"iteration":131,"passed_time":0.2423639908,"remaining_time":1.593726849},
{"learn":[5.070683732],"iteration":132,"passed_time":0.2429455696,"remaining_time":1.583712848},
{"learn":[5.06432037],"iteration":133,"passed_time":0.2435083398,"remaining_time":1.573718077},
{"learn":[5.057436484],"iteration":134,"passed_time":0.2440667713,"remaining_time":1.563835238},
{"learn":[5.053254656],"iteration":135,"passed_time":0.2446372473,"remaining_time":1.554166042},
{"learn":[5.04801663],"iteration":136,"passed_time":0.2452186657,"remaining_time":1.544698602},
{"learn":[5.045680836],"iteration":137,"passed_time":0.245671832,"remaining_time":1.534558835},
{"learn":[5.041857933],"iteration":138,"passed_time":0.2462572185,"remaining_time":1.525377447},
{"learn":[5.035264888],"iteration":139,"passed_time":0.2468361218,"remaining_time":1.516279034},
{"learn":[5.028771948],"iteration":140,"passed_time":0.2475360925,"remaining_time":1.508039032},
{"learn":[5.024912247],"iteration":141,"passed_time":0.2481134026,"remaining_time":1.49916408},
{"learn":[5.02239068],"iteration":142,"passed_time":0.2486836081,"remaining_time":1.490362602},
{"learn":[5.017110572],"iteration":143,"passed_time":0.2492890255,"remaining_time":1.481884763},
{"learn":[5.010707886],"iteration":144,"passed_time":0.2498994432,"remaining_time":1.473544993},
{"learn":[5.004389868],"iteration":145,"passed_time":0.2504699994,"remaining_time":1.465077942},
{"learn":[4.997628683],"iteration":146,"passed_time":0.2510573399,"remaining_time":1.456815721},
{"learn":[4.991497851],"iteration":147,"passed_time":0.2516436684,"remaining_time":1.448651388},
{"learn":[4.988345253],"iteration":148,"passed_time":0.2522269907,"remaining_time":1.440571605},
{"learn":[4.98460423],"iteration":149,"passed_time":0.252814692,"remaining_time":1.432616588},
{"learn":[4.982441783],"iteration":150,"passed_time":0.2533896071,"remaining_time":1.424687261},
{"learn":[4.977461771],"iteration":151,"passed_time":0.2539660052,"remaining_time":1.416862977},
{"learn":[4.973601586],"iteration":152,"passed_time":0.2548307831,"remaining_time":1.410729891},
{"learn":[4.968328804],"iteration":153,"passed_time":0.2556620319,"remaining_time":1.404481032},
{"learn":[4.9640736],"iteration":154,"passed_time":0.2563079421,"remaining_time":1.397291685},
{"learn":[4.960865882],"iteration":155,"passed_time":0.2568982788,"remaining_time":1.38988556},
{"learn":[4.957014156],"iteration":156,"passed_time":0.2574780538,"remaining_time":1.38250955},
{"learn":[4.952244852],"iteration":157,"passed_time":0.2580851547,"remaining_time":1.375365192},
{"learn":[4.949695675],"iteration":158,"passed_time":0.2586625149,"remaining_time":1.368145755},
{"learn":[4.946584698],"iteration":159,"passed_time":0.2592596554,"remaining_time":1.361113191},
{"learn":[4.940192834],"iteration":160,"passed_time":0.2598425168,"remaining_time":1.354086159},
{"learn":[4.936727994],"iteration":161,"passed_time":0.2604137844,"remaining_time":1.347078712},
{"learn":[4.932342063],"iteration":162,"passed_time":0.2610044017,"remaining_time":1.340249596},
{"learn":[4.925830838],"iteration":163,"passed_time":0.2616178355,"remaining_time":1.333612869},
{"learn":[4.922571773],"iteration":164,"passed_time":0.2622235837,"remaining_time":1.327010257},
{"learn":[4.918395814],"iteration":165,"passed_time":0.2628062546,"remaining_time":1.320363954},
{"learn":[4.911142452],"iteration":166,"passed_time":0.2633923426,"remaining_time":1.313807314},
{"learn":[4.908276131],"iteration":167,"passed_time":0.2639580288,"remaining_time":1.307220714},
{"learn":[4.904584645],"iteration":168,"passed_time":0.2645418121,"remaining_time":1.300794354},
{"learn":[4.89795517],"iteration":169,"passed_time":0.2651251745,"remaining_time":1.294434675},
{"learn":[4.895556491],"iteration":170,"passed_time":0.2657185273,"remaining_time":1.288190989},
{"learn":[4.890591233],"iteration":171,"passed_time":0.2663051564,"remaining_time":1.281980636},
{"learn":[4.884629277],"iteration":172,"passed_time":0.2669014652,"remaining_time":1.275881571},
{"learn":[4.880550786],"iteration":173,"passed_time":0.2674749073,"remaining_time":1.269737204},
{"learn":[4.876384842],"iteration":174,"passed_time":0.2680490609,"remaining_time":1.263659858},
{"learn":[4.872638238],"iteration":175,"passed_time":0.2686390568,"remaining_time":1.257719221},
{"learn":[4.869137118],"iteration":176,"passed_time":0.2692253352,"remaining_time":1.251821756},
{"learn":[4.863587157],"iteration":177,"passed_time":0.2700249699,"remaining_time":1.246969243},
{"learn":[4.858028614],"iteration":178,"passed_time":0.2709999926,"remaining_time":1.242966446},
{"learn":[4.853838176],"iteration":179,"passed_time":0.2715992575,"remaining_time":1.237285506},
{"learn":[4.853462329],"iteration":180,"passed_time":0.2718944608,"remaining_time":1.230284881},
{"learn":[4.851573196],"iteration":181,"passed_time":0.2724496557,"remaining_time":1.224526474},
{"learn":[4.848442087],"iteration":182,"passed_time":0.2730320962,"remaining_time":1.218946571},
{"learn":[4.845547104],"iteration":183,"passed_time":0.2735928123,"remaining_time":1.213324646},
{"learn":[4.839868817],"iteration":184,"passed_time":0.2741671161,"remaining_time":1.207817295},
{"learn":[4.836336958],"iteration":185,"passed_time":0.2747424621,"remaining_time":1.202367549},
{"learn":[4.831124789],"iteration":186,"passed_time":0.2752980077,"remaining_time":1.196883852},
{"learn":[4.827407333],"iteration":187,"passed_time":0.275860287,"remaining_time":1.191481665},
{"learn":[4.824088918],"iteration":188,"passed_time":0.2764808456,"remaining_time":1.186380772},
{"learn":[4.820934539],"iteration":189,"passed_time":0.277049007,"remaining_time":1.181103661},
{"learn":[4.816975227],"iteration":190,"passed_time":0.2776266777,"remaining_time":1.175916138},
{"learn":[4.812340486],"iteration":191,"passed_time":0.2781716316,"remaining_time":1.17063895},
{"learn":[4.806402747],"iteration":192,"passed_time":0.2787529899,"remaining_time":1.16556302},
{"learn":[4.801521788],"iteration":193,"passed_time":0.27932546,"remaining_time":1.160496499},
{"learn":[4.797601172],"iteration":194,"passed_time":0.2798927195,"remaining_time":1.15545456},
{"learn":[4.792694629],"iteration":195,"passed_time":0.2804744686,"remaining_time":1.150517718},
{"learn":[4.789794613],"iteration":196,"passed_time":0.2810317677,"remaining_time":1.145525429},
{"learn":[4.785367055],"iteration":197,"passed_time":0.2816004902,"remaining_time":1.140624208},
{"learn":[4.780376856],"iteration":198,"passed_time":0.2821686715,"remaining_time":1.135764351},
{"learn":[4.776691261],"iteration":199,"passed_time":0.2827395183,"remaining_time":1.130958073},
{"learn":[4.773470753],"iteration":200,"passed_time":0.2833325505,"remaining_time":1.126282129},
{"learn":[4.77207327],"iteration":201,"passed_time":0.2839029965,"remaining_time":1.121557382},
{"learn":[4.767347177],"iteration":202,"passed_time":0.2845074219,"remaining_time":1.117006972},
{"learn":[4.763983068],"iteration":203,"passed_time":0.2852159499,"remaining_time":1.112901451},
{"learn":[4.761588849],"iteration":204,"passed_time":0.285870989,"remaining_time":1.10862164},
{"learn":[4.758558086],"iteration":205,"passed_time":0.2864768073,"remaining_time":1.104187306},
{"learn":[4.753678804],"iteration":206,"passed_time":0.2870604102,"remaining_time":1.099704856},
{"learn":[4.746510889],"iteration":207,"passed_time":0.2876286617,"remaining_time":1.095201443},
{"learn":[4.744840601],"iteration":208,"passed_time":0.2881939171,"remaining_time":1.090724346},
{"learn":[4.741702222],"iteration":209,"passed_time":0.28877756,"remaining_time":1.086353678},
{"learn":[4.739352853],"iteration":210,"passed_time":0.2893628063,"remaining_time":1.082024901},
{"learn":[4.735539287],"iteration":211,"passed_time":0.2899512991,"remaining_time":1.077743508},
{"learn":[4.730726751],"iteration":212,"passed_time":0.2905313748,"remaining_time":1.07346569},
{"learn":[4.726416092],"iteration":213,"passed_time":0.2913034226,"remaining_time":1.069927524},
{"learn":[4.721293082],"iteration":214,"passed_time":0.2920665026,"remaining_time":1.066382347},
{"learn":[4.718443695],"iteration":215,"passed_time":0.2927694194,"remaining_time":1.062644559},
{"learn":[4.711627962],"iteration":216,"passed_time":0.2934894308,"remaining_time":1.058996425},
{"learn":[4.709790764],"iteration":217,"passed_time":0.294158679,"remaining_time":1.05519306},
{"learn":[4.706913073],"iteration":218,"passed_time":0.2948675379,"remaining_time":1.051559576},
{"learn":[4.703846389],"iteration":219,"passed_time":0.2955961171,"remaining_time":1.048022597},
{"learn":[4.701001135],"iteration":220,"passed_time":0.2962810471,"remaining_time":1.044357175},
{"learn":[4.700380864],"iteration":221,"passed_time":0.2969235504,"remaining_time":1.04056992},
{"learn":[4.695837486],"iteration":222,"passed_time":0.2976744151,"remaining_time":1.037188433},
{"learn":[4.691242996],"iteration":223,"passed_time":0.2983383671,"remaining_time":1.033529343},
{"learn":[4.690284609],"iteration":224,"passed_time":0.2989583343,"remaining_time":1.029745374},
{"learn":[4.68827119],"iteration":225,"passed_time":0.2995165052,"remaining_time":1.025777766},
{"learn":[4.686922425],"iteration":226,"passed_time":0.3004287368,"remaining_time":1.023045875},
{"learn":[4.686085874],"iteration":227,"passed_time":0.3011330261,"remaining_time":1.01962586},
{"learn":[4.683230741],"iteration":228,"passed_time":0.3017660801,"remaining_time":1.015989728},
{"learn":[4.6773487],"iteration":229,"passed_time":0.3023612867,"remaining_time":1.012253003},
{"learn":[4.671462906],"iteration":230,"passed_time":0.3029552006,"remaining_time":1.008539174},
{"learn":[4.664799601],"iteration":231,"passed_time":0.3035535637,"remaining_time":1.004866969},
{"learn":[4.660979386],"iteration":232,"passed_time":0.3041305831,"remaining_time":1.001150889},
{"learn":[4.656281279],"iteration":233,"passed_time":0.3047623645,"remaining_time":0.9976409025},
{"learn":[4.651997094],"iteration":234,"passed_time":0.3054603912,"remaining_time":0.9943710608},
{"learn":[4.650151977],"iteration":235,"passed_time":0.3060775429,"remaining_time":0.9908611984},
{"learn":[4.648478046],"iteration":236,"passed_time":0.3066300823,"remaining_time":0.9871677334},
{"learn":[4.646364602],"iteration":237,"passed_time":0.3072110298,"remaining_time":0.9835916164},
{"learn":[4.642635873],"iteration":238,"passed_time":0.307777658,"remaining_time":0.9799949695},
{"learn":[4.640860821],"iteration":239,"passed_time":0.3083308286,"remaining_time":0.9763809574},
{"learn":[4.639446822],"iteration":240,"passed_time":0.3089098121,"remaining_time":0.9728736405},
{"learn":[4.637120072],"iteration":241,"passed_time":0.3094746466,"remaining_time":0.9693462071},
{"learn":[4.633769267],"iteration":242,"passed_time":0.3100668871,"remaining_time":0.9659285332},
{"learn":[4.630491517],"iteration":243,"passed_time":0.3106340564,"remaining_time":0.9624563388},
{"learn":[4.627813333],"iteration":244,"passed_time":0.3112085106,"remaining_time":0.9590303082},
{"learn":[4.622496304],"iteration":245,"passed_time":0.3117839768,"remaining_time":0.9556305632},
{"learn":[4.618979301],"iteration":246,"passed_time":0.3123661969,"remaining_time":0.9522742764},
{"learn":[4.616563458],"iteration":247,"passed_time":0.3129345987,"remaining_time":0.9488984606},
{"learn":[4.614759385],"iteration":248,"passed_time":0.3134918878,"remaining_time":0.9455116777},
{"learn":[4.61251363],"iteration":249,"passed_time":0.3140604299,"remaining_time":0.9421812897},
{"learn":[4.608796693],"iteration":250,"passed_time":0.3146489829,"remaining_time":0.9389326223},
{"learn":[4.60847774],"iteration":251,"passed_time":0.3154495289,"remaining_time":0.9363343161},
{"learn":[4.605195659],"iteration":252,"passed_time":0.3161199195,"remaining_time":0.9333659283},
{"learn":[4.60103766],"iteration":253,"passed_time":0.3167893578,"remaining_time":0.9304128383},
{"learn":[4.599325598],"iteration":254,"passed_time":0.3173924906,"remaining_time":0.9272839431},
{"learn":[4.597012808],"iteration":255,"passed_time":0.3179695,"remaining_time":0.9240988594},
{"learn":[4.594161533],"iteration":256,"passed_time":0.3185696467,"remaining_time":0.921000963},
{"learn":[4.592197259],"iteration":257,"passed_time":0.3191634304,"remaining_time":0.9179041293},
{"learn":[4.58952828],"iteration":258,"passed_time":0.3197496085,"remaining_time":0.9148048646},
{"learn":[4.585816572],"iteration":259,"passed_time":0.3203249846,"remaining_time":0.9116941869},
{"learn":[4.582934052],"iteration":260,"passed_time":0.3208890175,"remaining_time":0.9085708196},
{"learn":[4.582234842],"iteration":261,"passed_time":0.3214542528,"remaining_time":0.9054703762},
{"learn":[4.57571562],"iteration":262,"passed_time":0.3220428659,"remaining_time":0.9024547232},
{"learn":[4.571197349],"iteration":263,"passed_time":0.3226288737,"remaining_time":0.8994501934},
{"learn":[4.56723703],"iteration":264,"passed_time":0.3232076167,"remaining_time":0.896443767},
{"learn":[4.560335567],"iteration":265,"passed_time":0.3237988151,"remaining_time":0.8934899634},
{"learn":[4.554709345],"iteration":266,"passed_time":0.324376065,"remaining_time":0.8905155641},
{"learn":[4.552806306],"iteration":267,"passed_time":0.3249422422,"remaining_time":0.8875288109},
{"learn":[4.550766241],"iteration":268,"passed_time":0.3255171674,"remaining_time":0.8845838266},
{"learn":[4.549216045],"iteration":269,"passed_time":0.3260960105,"remaining_time":0.8816669914},
{"learn":[4.547687452],"iteration":270,"passed_time":0.3266541213,"remaining_time":0.87871164},
{"learn":[4.545642435],"iteration":271,"passed_time":0.3272055284,"remaining_time":0.875755973},
{"learn":[4.543930359],"iteration":272,"passed_time":0.3277752028,"remaining_time":0.8728665657},
{"learn":[4.541029943],"iteration":273,"passed_time":0.3283590963,"remaining_time":0.870031766},
{"learn":[4.537781449],"iteration":274,"passed_time":0.3289189506,"remaining_time":0.8671499607},
{"learn":[4.53066128],"iteration":275,"passed_time":0.3295200593,"remaining_time":0.8643931989},
{"learn":[4.526763956],"iteration":276,"passed_time":0.3302482173,"remaining_time":0.8619836142},
{"learn":[4.522036004],"iteration":277,"passed_time":0.3309722778,"remaining_time":0.8595754842},
{"learn":[4.515307629],"iteration":278,"passed_time":0.3317849395,"remaining_time":0.8574083919},
{"learn":[4.51109143],"iteration":279,"passed_time":0.3324239656,"remaining_time":0.854804483},
{"learn":[4.508233494],"iteration":280,"passed_time":0.3330012656,"remaining_time":0.8520566192},
{"learn":[4.502555629],"iteration":281,"passed_time":0.3336643607,"remaining_time":0.8495425922},
{"learn":[4.500081355],"iteration":282,"passed_time":0.3342602287,"remaining_time":0.8468713214},
{"learn":[4.495281743],"iteration":283,"passed_time":0.3348692335,"remaining_time":0.8442477858},
{"learn":[4.492138869],"iteration":284,"passed_time":0.3354640793,"remaining_time":0.8416028657},
{"learn":[4.491708261],"iteration":285,"passed_time":0.336041219,"remaining_time":0.8389280782},
{"learn":[4.489398865],"iteration":286,"passed_time":0.3366062439,"remaining_time":0.8362378115},
{"learn":[4.485796373],"iteration":287,"passed_time":0.3372027231,"remaining_time":0.8336400654},
{"learn":[4.479542205],"iteration":288,"passed_time":0.3377878691,"remaining_time":0.831028287},
{"learn":[4.475986993],"iteration":289,"passed_time":0.3383466112,"remaining_time":0.8283658412},
{"learn":[4.468661855],"iteration":290,"passed_time":0.3389578506,"remaining_time":0.8258457596},
{"learn":[4.463785664],"iteration":291,"passed_time":0.3395326955,"remaining_time":0.8232505084},
{"learn":[4.460445831],"iteration":292,"passed_time":0.340109715,"remaining_time":0.8206742952},
{"learn":[4.45692492],"iteration":293,"passed_time":0.3406863937,"remaining_time":0.8181108638},
{"learn":[4.454031688],"iteration":294,"passed_time":0.3412581123,"remaining_time":0.815549048},
{"learn":[4.451672391],"iteration":295,"passed_time":0.3418369454,"remaining_time":0.8130175999},
{"learn":[4.45031553],"iteration":296,"passed_time":0.3424015695,"remaining_time":0.8104656679},
{"learn":[4.446782666],"iteration":297,"passed_time":0.3429825771,"remaining_time":0.8079656681},
{"learn":[4.444369689],"iteration":298,"passed_time":0.3436116529,"remaining_time":0.8055911996},
{"learn":[4.44411683],"iteration":299,"passed_time":0.3442016586,"remaining_time":0.8031372034},
{"learn":[4.440876943],"iteration":300,"passed_time":0.344803639,"remaining_time":0.800723401},
{"learn":[4.439336453],"iteration":301,"passed_time":0.3455414978,"remaining_time":0.7986356471},
{"learn":[4.436666901],"iteration":302,"passed_time":0.3462138019,"remaining_time":0.7964060064},
{"learn":[4.433043336],"iteration":303,"passed_time":0.3469798477,"remaining_time":0.7944012303},
{"learn":[4.431419305],"iteration":304,"passed_time":0.3475823993,"remaining_time":0.7920320247},
{"learn":[4.428859646],"iteration":305,"passed_time":0.348313153,"remaining_time":0.7899651248},
{"learn":[4.424552441],"iteration":306,"passed_time":0.3489413971,"remaining_time":0.7876755316},
{"learn":[4.422706391],"iteration":307,"passed_time":0.3496231609,"remaining_time":0.7855169719},
{"learn":[4.421427994],"iteration":308,"passed_time":0.3504656827,"remaining_time":0.7837274653},
{"learn":[4.418733158],"iteration":309,"passed_time":0.3512318187,"remaining_time":0.7817740481},
{"learn":[4.415656941],"iteration":310,"passed_time":0.3519933152,"remaining_time":0.7798179877},
{"learn":[4.410747417],"iteration":311,"passed_time":0.3526785959,"remaining_time":0.7777015192},
{"learn":[4.408126521],"iteration":312,"passed_time":0.3533475227,"remaining_time":0.7755583005},
{"learn":[4.407843853],"iteration":313,"passed_time":0.3539551046,"remaining_time":0.7732904514},
{"learn":[4.405219398],"iteration":314,"passed_time":0.3545591693,"remaining_time":0.7710254951},
{"learn":[4.402708465],"iteration":315,"passed_time":0.3551398662,"remaining_time":0.7687204699},
{"learn":[4.40104971],"iteration":316,"passed_time":0.3557177374,"remaining_time":0.7664202354},
{"learn":[4.400830038],"iteration":317,"passed_time":0.3562661383,"remaining_time":0.7640676299},
{"learn":[4.39784288],"iteration":318,"passed_time":0.3568569259,"remaining_time":0.7618168229},
{"learn":[4.393741845],"iteration":319,"passed_time":0.3574221211,"remaining_time":0.7595220074},
{"learn":[4.393425936],"iteration":320,"passed_time":0.3579966254,"remaining_time":0.7572576593},
{"learn":[4.390505974],"iteration":321,"passed_time":0.358573755,"remaining_time":0.7550093351},
{"learn":[4.390305136],"iteration":322,"passed_time":0.3591287595,"remaining_time":0.752724985},
{"learn":[4.38568203],"iteration":323,"passed_time":0.3597087853,"remaining_time":0.750503515},
{"learn":[4.383057135],"iteration":324,"passed_time":0.3602969074,"remaining_time":0.7483089616},
{"learn":[4.380662684],"iteration":325,"passed_time":0.3610215735,"remaining_time":0.7464065661},
{"learn":[4.37805727],"iteration":326,"passed_time":0.3616214096,"remaining_time":0.7442544606},
{"learn":[4.373708319],"iteration":327,"passed_time":0.3622147523,"remaining_time":0.742098517},
{"learn":[4.36887921],"iteration":328,"passed_time":0.3628987957,"remaining_time":0.7401370574},
{"learn":[4.367895929],"iteration":329,"passed_time":0.3634604637,"remaining_time":0.7379348809},
{"learn":[4.362140573],"iteration":330,"passed_time":0.3640617527,"remaining_time":0.7358226966},
{"learn":[4.361931924],"iteration":331,"passed_time":0.3646136909,"remaining_time":0.7336203178},
{"learn":[4.359656377],"iteration":332,"passed_time":0.3651891571,"remaining_time":0.7314749784},
{"learn":[4.354281355],"iteration":333,"passed_time":0.3657791431,"remaining_time":0.7293679919},
{"learn":[4.348589447],"iteration":334,"passed_time":0.3663646799,"remaining_time":0.7272612302},
{"learn":[4.346355698],"iteration":335,"passed_time":0.3669536987,"remaining_time":0.7251704046},
{"learn":[4.343894047],"iteration":336,"passed_time":0.3675538755,"remaining_time":0.7231104434},
{"learn":[4.341561356],"iteration":337,"passed_time":0.3681590825,"remaining_time":0.7210689722},
{"learn":[4.338869061],"iteration":338,"passed_time":0.3687661033,"remaining_time":0.7190395111},
{"learn":[4.333720063],"iteration":339,"passed_time":0.3693712902,"remaining_time":0.7170148575},
{"learn":[4.330892223],"iteration":340,"passed_time":0.3699526385,"remaining_time":0.7149524598},
{"learn":[4.328311474],"iteration":341,"passed_time":0.3705450995,"remaining_time":0.7129201037},
{"learn":[4.324580133],"iteration":342,"passed_time":0.3711237322,"remaining_time":0.7108696562},
{"learn":[4.323354432],"iteration":343,"passed_time":0.371701884,"remaining_time":0.7088268485},
{"learn":[4.323159553],"iteration":344,"passed_time":0.3722638226,"remaining_time":0.7067617501},
{"learn":[4.318639682],"iteration":345,"passed_time":0.3728531972,"remaining_time":0.7047571994},
{"learn":[4.312712208],"iteration":346,"passed_time":0.3734506484,"remaining_time":0.7027760041},
{"learn":[4.311461062],"iteration":347,"passed_time":0.3740197517,"remaining_time":0.7007496497},
{"learn":[4.311178356],"iteration":348,"passed_time":0.3745536029,"remaining_time":0.6986658896},
{"learn":[4.311102505],"iteration":349,"passed_time":0.3750966027,"remaining_time":0.6966079765},
{"learn":[4.310232308],"iteration":350,"passed_time":0.3757545324,"remaining_time":0.6947712009},
{"learn":[4.305128197],"iteration":351,"passed_time":0.3763870954,"remaining_time":0.6928944256},
{"learn":[4.304595496],"iteration":352,"passed_time":0.3769837051,"remaining_time":0.6909588023},
{"learn":[4.3004992],"iteration":353,"passed_time":0.3775820982,"remaining_time":0.6890339984},
{"learn":[4.297581524],"iteration":354,"passed_time":0.3781873553,"remaining_time":0.6871291386},
{"learn":[4.297355825],"iteration":355,"passed_time":0.3787601962,"remaining_time":0.6851729392},
{"learn":[4.295758715],"iteration":356,"passed_time":0.3793221348,"remaining_time":0.6832048535},
{"learn":[4.292500657],"iteration":357,"passed_time":0.3799050663,"remaining_time":0.6812822698},
{"learn":[4.290797586],"iteration":358,"passed_time":0.3804811539,"remaining_time":0.6793549293},
{"learn":[4.286410608],"iteration":359,"passed_time":0.3810670113,"remaining_time":0.6774524646},
{"learn":[4.280278245],"iteration":360,"passed_time":0.3816325673,"remaining_time":0.6755213588},
{"learn":[4.279941283],"iteration":361,"passed_time":0.3821740742,"remaining_time":0.6735554125},
{"learn":[4.274426275],"iteration":362,"passed_time":0.3827457326,"remaining_time":0.671650225},
{"learn":[4.273567658],"iteration":363,"passed_time":0.3833331433,"remaining_time":0.6697798877},
{"learn":[4.269488271],"iteration":364,"passed_time":0.3839350937,"remaining_time":0.6679418753},
{"learn":[4.266838205],"iteration":365,"passed_time":0.3845143076,"remaining_time":0.6660712323},
{"learn":[4.263456509],"iteration":366,"passed_time":0.3851069089,"remaining_time":0.6642307175},
{"learn":[4.260360204],"iteration":367,"passed_time":0.3856718235,"remaining_time":0.6623494361},
{"learn":[4.255120549],"iteration":368,"passed_time":0.3862597953,"remaining_time":0.6605147178},
{"learn":[4.252582211],"iteration":369,"passed_time":0.3868362636,"remaining_time":0.6586671516},
{"learn":[4.247857931],"iteration":370,"passed_time":0.3874337349,"remaining_time":0.6568620465},
{"learn":[4.245288911],"iteration":371,"passed_time":0.3880027279,"remaining_time":0.6550153578},
{"learn":[4.24048515],"iteration":372,"passed_time":0.3885949684,"remaining_time":0.6532145984},
{"learn":[4.2378365],"iteration":373,"passed_time":0.3891716973,"remaining_time":0.6513943382},
{"learn":[4.236751063],"iteration":374,"passed_time":0.3897436062,"remaining_time":0.649572677},
{"learn":[4.233240093],"iteration":375,"passed_time":0.3903314578,"remaining_time":0.6477841214},
{"learn":[4.230358421],"iteration":376,"passed_time":0.391077312,"remaining_time":0.6462630382},
{"learn":[4.225853583],"iteration":377,"passed_time":0.3917188236,"remaining_time":0.6445743605},
{"learn":[4.224702126],"iteration":378,"passed_time":0.3923169662,"remaining_time":0.6428201477},
{"learn":[4.224361982],"iteration":379,"passed_time":0.3929137259,"remaining_time":0.6410697634},
{"learn":[4.223787954],"iteration":380,"passed_time":0.3934900439,"remaining_time":0.6392922236},
{"learn":[4.22144054],"iteration":381,"passed_time":0.3940718331,"remaining_time":0.6375298242},
{"learn":[4.217739335],"iteration":382,"passed_time":0.3946685528,"remaining_time":0.6357976425},
{"learn":[4.215611665],"iteration":383,"passed_time":0.395255252,"remaining_time":0.6340553001},
{"learn":[4.210236863],"iteration":384,"passed_time":0.3958678642,"remaining_time":0.6323603544},
{"learn":[4.208454294],"iteration":385,"passed_time":0.3964829714,"remaining_time":0.6306749857},
{"learn":[4.207446501],"iteration":386,"passed_time":0.3970849819,"remaining_time":0.6289744029},
{"learn":[4.204985442],"iteration":387,"passed_time":0.3976771824,"remaining_time":0.6272640093},
{"learn":[4.202796622],"iteration":388,"passed_time":0.3982673387,"remaining_time":0.6255561541},
{"learn":[4.199774004],"iteration":389,"passed_time":0.3988865042,"remaining_time":0.6238994041},
{"learn":[4.199458358],"iteration":390,"passed_time":0.3994506073,"remaining_time":0.622162199},
{"learn":[4.19751254],"iteration":391,"passed_time":0.4000495415,"remaining_time":0.6204850031},
{"learn":[4.195201346],"iteration":392,"passed_time":0.4006150674,"remaining_time":0.6187616944},
{"learn":[4.190593508],"iteration":393,"passed_time":0.4012171481,"remaining_time":0.6171004866},
{"learn":[4.187212054],"iteration":394,"passed_time":0.4018344398,"remaining_time":0.6154679394},
{"learn":[4.184984466],"iteration":395,"passed_time":0.4024414305,"remaining_time":0.6138248081},
{"learn":[4.182832144],"iteration":396,"passed_time":0.4030234201,"remaining_time":0.6121489227},
{"learn":[4.179752812],"iteration":397,"passed_time":0.4036724664,"remaining_time":0.6105799618},
{"learn":[4.17878934],"iteration":398,"passed_time":0.4042565002,"remaining_time":0.6089176858},
{"learn":[4.174548229],"iteration":399,"passed_time":0.4048431894,"remaining_time":0.6072647841},
{"learn":[4.168872556],"iteration":400,"passed_time":0.4054454304,"remaining_time":0.6056404309},
{"learn":[4.163926494],"iteration":401,"passed_time":0.4061111711,"remaining_time":0.6041156227},
{"learn":[4.159485076],"iteration":402,"passed_time":0.4067378523,"remaining_time":0.6025372155},
{"learn":[4.155926102],"iteration":403,"passed_time":0.4073362655,"remaining_time":0.6009218174},
{"learn":[4.153540115],"iteration":404,"passed_time":0.4079178041,"remaining_time":0.5992866505},
{"learn":[4.150983044],"iteration":405,"passed_time":0.4084969579,"remaining_time":0.5976531847},
{"learn":[4.146539132],"iteration":406,"passed_time":0.4090960324,"remaining_time":0.5960539244},
{"learn":[4.144869174],"iteration":407,"passed_time":0.4096653361,"remaining_time":0.59441637},
{"learn":[4.142825962],"iteration":408,"passed_time":0.4102352209,"remaining_time":0.5927848791},
{"learn":[4.142467378],"iteration":409,"passed_time":0.410792019,"remaining_time":0.5911397347},
{"learn":[4.141800768],"iteration":410,"passed_time":0.4113490576,"remaining_time":0.589500231},
{"learn":[4.140107084],"iteration":411,"passed_time":0.4119373601,"remaining_time":0.5879106013},
{"learn":[4.136243196],"iteration":412,"passed_time":0.4125211934,"remaining_time":0.5863194686},
{"learn":[4.133618439],"iteration":413,"passed_time":0.4131057883,"remaining_time":0.5847342801},
{"learn":[4.131053025],"iteration":414,"passed_time":0.413701506,"remaining_time":0.5831695928},
{"learn":[4.128379975],"iteration":415,"passed_time":0.4142845277,"remaining_time":0.5815917408},
{"learn":[4.127068571],"iteration":416,"passed_time":0.4148599739,"remaining_time":0.580008069},
{"learn":[4.125969877],"iteration":417,"passed_time":0.4154150885,"remaining_time":0.5784009127},
{"learn":[4.123893633],"iteration":418,"passed_time":0.4160028299,"remaining_time":0.5768440195},
{"learn":[4.119643722],"iteration":419,"passed_time":0.416582635,"remaining_time":0.5752807816},
{"learn":[4.11465686],"iteration":420,"passed_time":0.4171690135,"remaining_time":0.5737312561},
{"learn":[4.111565986],"iteration":421,"passed_time":0.4177498007,"remaining_time":0.5721786369},
{"learn":[4.106322452],"iteration":422,"passed_time":0.4183423017,"remaining_time":0.5706465912},
{"learn":[4.104222175],"iteration":423,"passed_time":0.4189421478,"remaining_time":0.5691289555},
{"learn":[4.103008002],"iteration":424,"passed_time":0.4195500804,"remaining_time":0.5676265794},
{"learn":[4.099176337],"iteration":425,"passed_time":0.4201508384,"remaining_time":0.5661187353},
{"learn":[4.096525716],"iteration":426,"passed_time":0.4207551132,"remaining_time":0.5646198592},
{"learn":[4.094967724],"iteration":427,"passed_time":0.4214240727,"remaining_time":0.5632116112},
{"learn":[4.094683584],"iteration":428,"passed_time":0.4220071545,"remaining_time":0.5616925064},
{"learn":[4.091096563],"iteration":429,"passed_time":0.4225994652,"remaining_time":0.5601899888},
{"learn":[4.089178677],"iteration":430,"passed_time":0.4231733683,"remaining_time":0.5586673934},
{"learn":[4.085335077],"iteration":431,"passed_time":0.4237696471,"remaining_time":0.55717861},
{"learn":[4.084852122],"iteration":432,"passed_time":0.4243482998,"remaining_time":0.5556708684},
{"learn":[4.080322952],"iteration":433,"passed_time":0.4249289467,"remaining_time":0.5541700088},
{"learn":[4.077449519],"iteration":434,"passed_time":0.4255177201,"remaining_time":0.5526839353},
{"learn":[4.076568374],"iteration":435,"passed_time":0.4260797389,"remaining_time":0.5511673686},
{"learn":[4.076071793],"iteration":436,"passed_time":0.4266581311,"remaining_time":0.549676265},
{"learn":[4.075027644],"iteration":437,"passed_time":0.4272295892,"remaining_time":0.5481804318},
{"learn":[4.07020837],"iteration":438,"passed_time":0.4278036125,"remaining_time":0.5466920879},
{"learn":[4.06833694],"iteration":439,"passed_time":0.4283900612,"remaining_time":0.5452237142},
{"learn":[4.063936568],"iteration":440,"passed_time":0.4289845663,"remaining_time":0.5437695523},
{"learn":[4.061734926],"iteration":441,"passed_time":0.4295708246,"remaining_time":0.5423088691},
{"learn":[4.060815619],"iteration":442,"passed_time":0.4301521929,"remaining_time":0.5408459853},
{"learn":[4.056407489],"iteration":443,"passed_time":0.4307542836,"remaining_time":0.5394130218},
{"learn":[4.05238936],"iteration":444,"passed_time":0.4313378664,"remaining_time":0.5379607098},
{"learn":[4.049685254],"iteration":445,"passed_time":0.4319269806,"remaining_time":0.5365191642},
{"learn":[4.045162016],"iteration":446,"passed_time":0.4325208144,"remaining_time":0.5350872715},
{"learn":[4.042955482],"iteration":447,"passed_time":0.4330857491,"remaining_time":0.5336235123},
{"learn":[4.041467663],"iteration":448,"passed_time":0.433663961,"remaining_time":0.5321800501},
{"learn":[4.038920476],"iteration":449,"passed_time":0.434222703,"remaining_time":0.530716637},
{"learn":[4.036694383],"iteration":450,"passed_time":0.4348064061,"remaining_time":0.5292876207},
{"learn":[4.034999007],"iteration":451,"passed_time":0.43541115,"remaining_time":0.5278878545},
{"learn":[4.031928018],"iteration":452,"passed_time":0.436006036,"remaining_time":0.5264796947},
{"learn":[4.028718143],"iteration":453,"passed_time":0.4366215162,"remaining_time":0.5250998851},
{"learn":[4.027401978],"iteration":454,"passed_time":0.4372108608,"remaining_time":0.52369213},
{"learn":[4.025930598],"iteration":455,"passed_time":0.4377780401,"remaining_time":0.5222615215},
{"learn":[4.021074523],"iteration":456,"passed_time":0.4383865238,"remaining_time":0.520883769},
{"learn":[4.020268486],"iteration":457,"passed_time":0.4389572805,"remaining_time":0.5194647293},
{"learn":[4.017986361],"iteration":458,"passed_time":0.439524079,"remaining_time":0.5180447206},
{"learn":[4.014814804],"iteration":459,"passed_time":0.4401171312,"remaining_time":0.516659241},
{"learn":[4.009704796],"iteration":460,"passed_time":0.4407182799,"remaining_time":0.5152866657},
{"learn":[4.008440457],"iteration":461,"passed_time":0.4412734647,"remaining_time":0.5138639048},
{"learn":[4.004854849],"iteration":462,"passed_time":0.4418551136,"remaining_time":0.5124755853},
{"learn":[4.000898028],"iteration":463,"passed_time":0.4424475445,"remaining_time":0.511103198},
{"learn":[3.996617985],"iteration":464,"passed_time":0.4430383421,"remaining_time":0.5097322861},
{"learn":[3.995443319],"iteration":465,"passed_time":0.4436140889,"remaining_time":0.5083474753},
{"learn":[3.990771995],"iteration":466,"passed_time":0.4442125622,"remaining_time":0.5069920678},
{"learn":[3.989249359],"iteration":467,"passed_time":0.4447932892,"remaining_time":0.5056197219},
{"learn":[3.986599538],"iteration":468,"passed_time":0.4453710702,"remaining_time":0.5042474164},
{"learn":[3.985628919],"iteration":469,"passed_time":0.4459349828,"remaining_time":0.502862853},
{"learn":[3.985086112],"iteration":470,"passed_time":0.4465120023,"remaining_time":0.5014964951},
{"learn":[3.98466839],"iteration":471,"passed_time":0.4470654836,"remaining_time":0.5001071511},
{"learn":[3.984233894],"iteration":472,"passed_time":0.4476304985,"remaining_time":0.4987341917},
{"learn":[3.981855845],"iteration":473,"passed_time":0.4482049426,"remaining_time":0.4973751051},
{"learn":[3.978684264],"iteration":474,"passed_time":0.4487847778,"remaining_time":0.4960252807},
{"learn":[3.974361269],"iteration":475,"passed_time":0.449380766,"remaining_time":0.4946964735},
{"learn":[3.972074049],"iteration":476,"passed_time":0.4500771074,"remaining_time":0.4934807698},
{"learn":[3.97191982],"iteration":477,"passed_time":0.4506610009,"remaining_time":0.4921444403},
{"learn":[3.969616848],"iteration":478,"passed_time":0.4512647149,"remaining_time":0.490832811},
{"learn":[3.968533527],"iteration":479,"passed_time":0.451833267,"remaining_time":0.4894860392},
{"learn":[3.967568753],"iteration":480,"passed_time":0.4523956966,"remaining_time":0.4881358971},
{"learn":[3.966232553],"iteration":481,"passed_time":0.4529572444,"remaining_time":0.4867880759},
{"learn":[3.961522393],"iteration":482,"passed_time":0.4535578119,"remaining_time":0.485485277},
{"learn":[3.955829553],"iteration":483,"passed_time":0.454150313,"remaining_time":0.48417678},
{"learn":[3.954248095],"iteration":484,"passed_time":0.4547273926,"remaining_time":0.4828548601},
{"learn":[3.951922606],"iteration":485,"passed_time":0.4553032496,"remaining_time":0.4815347125},
{"learn":[3.94978202],"iteration":486,"passed_time":0.4558852993,"remaining_time":0.4802241449},
{"learn":[3.949518999],"iteration":487,"passed_time":0.4564411254,"remaining_time":0.4788890496},
{"learn":[3.945431216],"iteration":488,"passed_time":0.457018706,"remaining_time":0.4775798748},
{"learn":[3.943249086],"iteration":489,"passed_time":0.4576120287,"remaining_time":0.4762900707},
{"learn":[3.941981548],"iteration":490,"passed_time":0.4581981987,"remaining_time":0.4749956887},
{"learn":[3.936600517],"iteration":491,"passed_time":0.4588034258,"remaining_time":0.4737238624},
{"learn":[3.934476885],"iteration":492,"passed_time":0.4593995844,"remaining_time":0.4724454143},
{"learn":[3.93045798],"iteration":493,"passed_time":0.4600206137,"remaining_time":0.4711952036},
{"learn":[3.925977375],"iteration":494,"passed_time":0.4606025733,"remaining_time":0.4699076758},
{"learn":[3.92457993],"iteration":495,"passed_time":0.4611984212,"remaining_time":0.4686371054},
{"learn":[3.919849146],"iteration":496,"passed_time":0.461785441,"remaining_time":0.4673603156},
{"learn":[3.919681964],"iteration":497,"passed_time":0.4623360064,"remaining_time":0.4660495486},
{"learn":[3.917633027],"iteration":498,"passed_time":0.4629217035,"remaining_time":0.4647771012},
{"learn":[3.916616419],"iteration":499,"passed_time":0.4635013383,"remaining_time":0.4635013383},
{"learn":[3.912896166],"iteration":500,"passed_time":0.4640875265,"remaining_time":0.4622348817},
{"learn":[3.912769674],"iteration":501,"passed_time":0.4646513289,"remaining_time":0.4609489279},
{"learn":[3.909373788],"iteration":502,"passed_time":0.4652549828,"remaining_time":0.4597052215},
{"learn":[3.906706036],"iteration":503,"passed_time":0.4658581456,"remaining_time":0.4584635719},
{"learn":[3.903895664],"iteration":504,"passed_time":0.4664417886,"remaining_time":0.4572053175},
{"learn":[3.902982967],"iteration":505,"passed_time":0.4671387109,"remaining_time":0.4560603225},
{"learn":[3.900905528],"iteration":506,"passed_time":0.4677362523,"remaining_time":0.4548204583},
{"learn":[3.897463465],"iteration":507,"passed_time":0.4683383931,"remaining_time":0.4535875775},
{"learn":[3.895918033],"iteration":508,"passed_time":0.4688942693,"remaining_time":0.4523125466},
{"learn":[3.893921936],"iteration":509,"passed_time":0.469466078,"remaining_time":0.4510556436},
{"learn":[3.890237934],"iteration":510,"passed_time":0.4700485586,"remaining_time":0.4498116344},
{"learn":[3.887311613],"iteration":511,"passed_time":0.4706434646,"remaining_time":0.4485820522},
{"learn":[3.884869735],"iteration":512,"passed_time":0.471254724,"remaining_time":0.447370469},
{"learn":[3.882101231],"iteration":513,"passed_time":0.4718293385,"remaining_time":0.446126573},
{"learn":[3.88060368],"iteration":514,"passed_time":0.472405907,"remaining_time":0.4448871163},
{"learn":[3.877726076],"iteration":515,"passed_time":0.4729968048,"remaining_time":0.4436636696},
{"learn":[3.874938145],"iteration":516,"passed_time":0.4735801071,"remaining_time":0.4424355739},
{"learn":[3.874340833],"iteration":517,"passed_time":0.4741707944,"remaining_time":0.4412168396},
{"learn":[3.873105224],"iteration":518,"passed_time":0.4747458098,"remaining_time":0.439986001},
{"learn":[3.869800236],"iteration":519,"passed_time":0.4753367376,"remaining_time":0.4387723732},
{"learn":[3.867932518],"iteration":520,"passed_time":0.4759003897,"remaining_time":0.4375360589},
{"learn":[3.866666962],"iteration":521,"passed_time":0.4764850147,"remaining_time":0.4363215269},
{"learn":[3.865527652],"iteration":522,"passed_time":0.4770618237,"remaining_time":0.4351022751},
{"learn":[3.861900081],"iteration":523,"passed_time":0.477653974,"remaining_time":0.4338994115},
{"learn":[3.858502887],"iteration":524,"passed_time":0.4782574776,"remaining_time":0.4327091464},
{"learn":[3.858335097],"iteration":525,"passed_time":0.4788187849,"remaining_time":0.4314830875},
{"learn":[3.855719306],"iteration":526,"passed_time":0.479432339,"remaining_time":0.4303064447},
{"learn":[3.855137428],"iteration":527,"passed_time":0.4800148897,"remaining_time":0.4291042196},
{"learn":[3.851985706],"iteration":528,"passed_time":0.4805963783,"remaining_time":0.4279033916},
{"learn":[3.851051809],"iteration":529,"passed_time":0.4811603711,"remaining_time":0.4266893857},
{"learn":[3.850679146],"iteration":530,"passed_time":0.4817088522,"remaining_time":0.4254641274},
{"learn":[3.848179484],"iteration":531,"passed_time":0.482331465,"remaining_time":0.4243066271},
{"learn":[3.844551071],"iteration":532,"passed_time":0.4829290766,"remaining_time":0.4231292284},
{"learn":[3.841604794],"iteration":533,"passed_time":0.4835096232,"remaining_time":0.4219391094},
{"learn":[3.83969656],"iteration":534,"passed_time":0.4840887569,"remaining_time":0.4207500411},
{"learn":[3.836811463],"iteration":535,"passed_time":0.4846834024,"remaining_time":0.4195766767},
{"learn":[3.834182551],"iteration":536,"passed_time":0.485252706,"remaining_time":0.4183836181},
{"learn":[3.828012842],"iteration":537,"passed_time":0.4858350864,"remaining_time":0.4172041077},
{"learn":[3.826636176],"iteration":538,"passed_time":0.4863975661,"remaining_time":0.4160097922},
{"learn":[3.826189798],"iteration":539,"passed_time":0.4869486325,"remaining_time":0.4148080944},
{"learn":[3.824104738],"iteration":540,"passed_time":0.4875341693,"remaining_time":0.4136380475},
{"learn":[3.82300218],"iteration":541,"passed_time":0.4880915586,"remaining_time":0.4124463724},
{"learn":[3.817146402],"iteration":542,"passed_time":0.4886746004,"remaining_time":0.4112786231},
{"learn":[3.814638044],"iteration":543,"passed_time":0.4892837054,"remaining_time":0.4101348707},
{"learn":[3.812979573],"iteration":544,"passed_time":0.4898678093,"remaining_time":0.4089722077},
{"learn":[3.811938825],"iteration":545,"passed_time":0.4904303792,"remaining_time":0.4077937585},
{"learn":[3.811479418],"iteration":546,"passed_time":0.490995374,"remaining_time":0.4066195693},
{"learn":[3.80742981],"iteration":547,"passed_time":0.4915833659,"remaining_time":0.4054665718},
{"learn":[3.805097043],"iteration":548,"passed_time":0.4921708066,"remaining_time":0.4043151799},
{"learn":[3.801577232],"iteration":549,"passed_time":0.4927843907,"remaining_time":0.4031872288},
{"learn":[3.799762083],"iteration":550,"passed_time":0.493384337,"remaining_time":0.4020500314},
{"learn":[3.796393455],"iteration":551,"passed_time":0.4940045396,"remaining_time":0.4009312205},
{"learn":[3.793486459],"iteration":552,"passed_time":0.4946045159,"remaining_time":0.3997978637},
{"learn":[3.792006091],"iteration":553,"passed_time":0.4951987906,"remaining_time":0.3986618423},
{"learn":[3.78932128],"iteration":554,"passed_time":0.4957915522,"remaining_time":0.3975265599},
{"learn":[3.787581812],"iteration":555,"passed_time":0.4963772494,"remaining_time":0.3963875876},
{"learn":[3.785308865],"iteration":556,"passed_time":0.4969589684,"remaining_time":0.3952474381},
{"learn":[3.78465475],"iteration":557,"passed_time":0.4975552621,"remaining_time":0.3941208348},
{"learn":[3.780498869],"iteration":558,"passed_time":0.4981446969,"remaining_time":0.3929907179},
{"learn":[3.778734909],"iteration":559,"passed_time":0.4987251634,"remaining_time":0.3918554855},
{"learn":[3.778652349],"iteration":560,"passed_time":0.4992764502,"remaining_time":0.3906993969},
{"learn":[3.777928006],"iteration":561,"passed_time":0.4998442407,"remaining_time":0.3895583229},
{"learn":[3.776131406],"iteration":562,"passed_time":0.5004165906,"remaining_time":0.3884228243},
{"learn":[3.772925617],"iteration":563,"passed_time":0.5009900428,"remaining_time":0.3872901749},
{"learn":[3.7727745],"iteration":564,"passed_time":0.5015336639,"remaining_time":0.3861365377},
{"learn":[3.771763073],"iteration":565,"passed_time":0.5021145212,"remaining_time":0.3850136081},
{"learn":[3.768738162],"iteration":566,"passed_time":0.5027077337,"remaining_time":0.3839020259},
{"learn":[3.767220794],"iteration":567,"passed_time":0.503281276,"remaining_time":0.3827773085},
{"learn":[3.766691102],"iteration":568,"passed_time":0.5038487259,"remaining_time":0.3816499136},
{"learn":[3.766259335],"iteration":569,"passed_time":0.5044078688,"remaining_time":0.3805182168},
{"learn":[3.76116362],"iteration":570,"passed_time":0.5049983156,"remaining_time":0.3794120445},
{"learn":[3.758633056],"iteration":571,"passed_time":0.5055799645,"remaining_time":0.3783010923},
{"learn":[3.754603809],"iteration":572,"passed_time":0.5061718944,"remaining_time":0.3771996491},
{"learn":[3.754070549],"iteration":573,"passed_time":0.5067403764,"remaining_time":0.376082579},
{"learn":[3.750534319],"iteration":574,"passed_time":0.5073207126,"remaining_time":0.3749761789},
{"learn":[3.746491516],"iteration":575,"passed_time":0.5079184143,"remaining_time":0.3738843883},
{"learn":[3.744210544],"iteration":576,"passed_time":0.5085723962,"remaining_time":0.3728355695},
{"learn":[3.742929991],"iteration":577,"passed_time":0.5093149439,"remaining_time":0.3718527791},
{"learn":[3.740402992],"iteration":578,"passed_time":0.5100892265,"remaining_time":0.3708938936},
{"learn":[3.739644243],"iteration":579,"passed_time":0.5109074192,"remaining_time":0.3699674415},
{"learn":[3.737529404],"iteration":580,"passed_time":0.5116493858,"remaining_time":0.3689863901},
{"learn":[3.737196923],"iteration":581,"passed_time":0.5123819128,"remaining_time":0.3679993807},
{"learn":[3.733954464],"iteration":582,"passed_time":0.5130729756,"remaining_time":0.3669835863},
{"learn":[3.731608623],"iteration":583,"passed_time":0.513770852,"remaining_time":0.3659737576},
{"learn":[3.729843952],"iteration":584,"passed_time":0.514543331,"remaining_time":0.3650179186},
{"learn":[3.727223798],"iteration":585,"passed_time":0.5153161804,"remaining_time":0.364062967},
{"learn":[3.725351667],"iteration":586,"passed_time":0.5160675863,"remaining_time":0.3630935488},
{"learn":[3.725026912],"iteration":587,"passed_time":0.5167971979,"remaining_time":0.3621096012},
{"learn":[3.721974565],"iteration":588,"passed_time":0.5175772022,"remaining_time":0.361161681},
{"learn":[3.720269493],"iteration":589,"passed_time":0.5183336684,"remaining_time":0.3601979729},
{"learn":[3.718907466],"iteration":590,"passed_time":0.5191034117,"remaining_time":0.3592441547},
{"learn":[3.715602912],"iteration":591,"passed_time":0.5199486892,"remaining_time":0.3583430155},
{"learn":[3.714463059],"iteration":592,"passed_time":0.5207195348,"remaining_time":0.3573909792},
{"learn":[3.710802077],"iteration":593,"passed_time":0.5214760909,"remaining_time":0.3564297861},
{"learn":[3.708032435],"iteration":594,"passed_time":0.522271998,"remaining_time":0.3554960659},
{"learn":[3.703788939],"iteration":595,"passed_time":0.5230714221,"remaining_time":0.3545651921},
{"learn":[3.702500944],"iteration":596,"passed_time":0.5238560057,"remaining_time":0.3536247409},
{"learn":[3.698196925],"iteration":597,"passed_time":0.5246471425,"remaining_time":0.3526892162},
{"learn":[3.69658891],"iteration":598,"passed_time":0.5254529499,"remaining_time":0.3517639948},
{"learn":[3.696124066],"iteration":599,"passed_time":0.5262562518,"remaining_time":0.3508375012},
{"learn":[3.693537052],"iteration":600,"passed_time":0.5269246077,"remaining_time":0.3498218277},
{"learn":[3.691343275],"iteration":601,"passed_time":0.5276715647,"remaining_time":0.3488592737},
{"learn":[3.690973831],"iteration":602,"passed_time":0.5282716813,"remaining_time":0.3478007587},
{"learn":[3.686151073],"iteration":603,"passed_time":0.52898531,"remaining_time":0.3468181834},
{"learn":[3.683921982],"iteration":604,"passed_time":0.5295918397,"remaining_time":0.345766573},
{"learn":[3.679975271],"iteration":605,"passed_time":0.530357284,"remaining_time":0.3448197523},
{"learn":[3.674047638],"iteration":606,"passed_time":0.5311253242,"remaining_time":0.3438752099},
{"learn":[3.673151794],"iteration":607,"passed_time":0.5317284369,"remaining_time":0.3428249133},
{"learn":[3.670953108],"iteration":608,"passed_time":0.5324552322,"remaining_time":0.3418554939},
{"learn":[3.6703947],"iteration":609,"passed_time":0.5332018586,"remaining_time":0.3408995489},
{"learn":[3.668433805],"iteration":610,"passed_time":0.5339410993,"remaining_time":0.339939587},
{"learn":[3.668304956],"iteration":611,"passed_time":0.5346136643,"remaining_time":0.3389380748},
{"learn":[3.667880012],"iteration":612,"passed_time":0.5354101623,"remaining_time":0.3380158774},
{"learn":[3.667282264],"iteration":613,"passed_time":0.536212973,"remaining_time":0.3370980579},
{"learn":[3.664611483],"iteration":614,"passed_time":0.5369220226,"remaining_time":0.3361219166},
{"learn":[3.662543394],"iteration":615,"passed_time":0.5376030846,"remaining_time":0.3351291956},
{"learn":[3.659041959],"iteration":616,"passed_time":0.5383424161,"remaining_time":0.3341736554},
{"learn":[3.656868545],"iteration":617,"passed_time":0.5391187546,"remaining_time":0.3332416897},
{"learn":[3.654785614],"iteration":618,"passed_time":0.5398283398,"remaining_time":0.3322691397},
{"learn":[3.654566096],"iteration":619,"passed_time":0.5405705168,"remaining_time":0.3313174135},
{"learn":[3.651007045],"iteration":620,"passed_time":0.5412386024,"remaining_time":0.3303211438},
{"learn":[3.648921786],"iteration":621,"passed_time":0.5418911863,"remaining_time":0.3293165087},
{"learn":[3.647655706],"iteration":622,"passed_time":0.5424926256,"remaining_time":0.3282820543},
{"learn":[3.647241144],"iteration":623,"passed_time":0.5430796254,"remaining_time":0.3272402871},
{"learn":[3.644195689],"iteration":624,"passed_time":0.5437039816,"remaining_time":0.326222389},
{"learn":[3.642632246],"iteration":625,"passed_time":0.5444761897,"remaining_time":0.3252940814},
{"learn":[3.642523322],"iteration":626,"passed_time":0.5449431842,"remaining_time":0.3241847013},
{"learn":[3.641494659],"iteration":627,"passed_time":0.5455187006,"remaining_time":0.3231416507},
{"learn":[3.63976496],"iteration":628,"passed_time":0.5461067325,"remaining_time":0.3221074686},
{"learn":[3.637945652],"iteration":629,"passed_time":0.5466811166,"remaining_time":0.3210666875},
{"learn":[3.636233667],"iteration":630,"passed_time":0.5472514323,"remaining_time":0.3200250056},
{"learn":[3.635304404],"iteration":631,"passed_time":0.5478302754,"remaining_time":0.3189897806},
{"learn":[3.632234951],"iteration":632,"passed_time":0.5484123452,"remaining_time":0.3179578684},
{"learn":[3.631630987],"iteration":633,"passed_time":0.5489628704,"remaining_time":0.316909165},
{"learn":[3.630301009],"iteration":634,"passed_time":0.5496184507,"remaining_time":0.3159224166},
{"learn":[3.629077964],"iteration":635,"passed_time":0.5502067432,"remaining_time":0.3148981989},
{"learn":[3.628004522],"iteration":636,"passed_time":0.5507799548,"remaining_time":0.313866756},
{"learn":[3.625062876],"iteration":637,"passed_time":0.5513697504,"remaining_time":0.3128461593},
{"learn":[3.624917986],"iteration":638,"passed_time":0.5519410481,"remaining_time":0.3118164607},
{"learn":[3.622887087],"iteration":639,"passed_time":0.5525316653,"remaining_time":0.3107990617},
{"learn":[3.621220865],"iteration":640,"passed_time":0.5531267216,"remaining_time":0.3097854806},
{"learn":[3.621143844],"iteration":641,"passed_time":0.5536810647,"remaining_time":0.3087505002},
{"learn":[3.620822821],"iteration":642,"passed_time":0.5542390652,"remaining_time":0.3077190455},
{"learn":[3.619202826],"iteration":643,"passed_time":0.554818229,"remaining_time":0.3067007601},
{"learn":[3.618204882],"iteration":644,"passed_time":0.5555240314,"remaining_time":0.3057535367},
{"learn":[3.614259666],"iteration":645,"passed_time":0.5561409424,"remaining_time":0.3047583492},
{"learn":[3.613415661],"iteration":646,"passed_time":0.5567446163,"remaining_time":0.303757109},
{"learn":[3.611096773],"iteration":647,"passed_time":0.5573219062,"remaining_time":0.3027427639},
{"learn":[3.610820695],"iteration":648,"passed_time":0.5578937451,"remaining_time":0.3017268174},
{"learn":[3.609290065],"iteration":649,"passed_time":0.5584987769,"remaining_time":0.3007301106},
{"learn":[3.60897947],"iteration":650,"passed_time":0.5592596792,"remaining_time":0.299818169},
{"learn":[3.606570702],"iteration":651,"passed_time":0.5600555941,"remaining_time":0.2989253785},
{"learn":[3.606292637],"iteration":652,"passed_time":0.5606542278,"remaining_time":0.2979280506},
{"learn":[3.602753838],"iteration":653,"passed_time":0.5612602064,"remaining_time":0.2969358278},
{"learn":[3.599755869],"iteration":654,"passed_time":0.5618624574,"remaining_time":0.2959428211},
{"learn":[3.599509575],"iteration":655,"passed_time":0.5624453989,"remaining_time":0.2949408799},
{"learn":[3.595337722],"iteration":656,"passed_time":0.5630647348,"remaining_time":0.2939592147},
{"learn":[3.595168561],"iteration":657,"passed_time":0.5636193084,"remaining_time":0.2929449901},
{"learn":[3.59290559],"iteration":658,"passed_time":0.5642227818,"remaining_time":0.2919574637},
{"learn":[3.592015928],"iteration":659,"passed_time":0.5647968452,"remaining_time":0.2909559506},
{"learn":[3.590680403],"iteration":660,"passed_time":0.5653509779,"remaining_time":0.2899455091},
{"learn":[3.590361532],"iteration":661,"passed_time":0.5659184478,"remaining_time":0.2889432558},
{"learn":[3.589069739],"iteration":662,"passed_time":0.5664744342,"remaining_time":0.2879364771},
{"learn":[3.585010186],"iteration":663,"passed_time":0.5670591995,"remaining_time":0.286945619},
{"learn":[3.582997552],"iteration":664,"passed_time":0.5676635948,"remaining_time":0.2859658711},
{"learn":[3.582119256],"iteration":665,"passed_time":0.5682397224,"remaining_time":0.284973074},
{"learn":[3.579019356],"iteration":666,"passed_time":0.5688344481,"remaining_time":0.2839908114},
{"learn":[3.57719559],"iteration":667,"passed_time":0.5694147241,"remaining_time":0.2830025276},
{"learn":[3.574050046],"iteration":668,"passed_time":0.5700382085,"remaining_time":0.2820368416},
{"learn":[3.572204518],"iteration":669,"passed_time":0.57077279,"remaining_time":0.2811268966},
{"learn":[3.569508025],"iteration":670,"passed_time":0.5714362661,"remaining_time":0.2801826104},
{"learn":[3.566268704],"iteration":671,"passed_time":0.5720832185,"remaining_time":0.2792310948},
{"learn":[3.562564052],"iteration":672,"passed_time":0.5728030599,"remaining_time":0.2783158998},
{"learn":[3.561173586],"iteration":673,"passed_time":0.5735939865,"remaining_time":0.2774356671},
{"learn":[3.559551904],"iteration":674,"passed_time":0.5742486847,"remaining_time":0.2764901075},
{"learn":[3.558593054],"iteration":675,"passed_time":0.574871287,"remaining_time":0.2755300251},
{"learn":[3.555647008],"iteration":676,"passed_time":0.575572721,"remaining_time":0.2746085508},
{"learn":[3.553100059],"iteration":677,"passed_time":0.5762008349,"remaining_time":0.2736529039},
{"learn":[3.55085578],"iteration":678,"passed_time":0.5768020337,"remaining_time":0.2726854975},
{"learn":[3.550737965],"iteration":679,"passed_time":0.5775227368,"remaining_time":0.2717754056},
{"learn":[3.549408772],"iteration":680,"passed_time":0.5783835764,"remaining_time":0.2709315138},
{"learn":[3.547390589],"iteration":681,"passed_time":0.5791686614,"remaining_time":0.2700522497},
{"learn":[3.54723575],"iteration":682,"passed_time":0.5800223661,"remaining_time":0.2692051099},
{"learn":[3.543988891],"iteration":683,"passed_time":0.580729151,"remaining_time":0.2682900756},
{"learn":[3.543868508],"iteration":684,"passed_time":0.5813918956,"remaining_time":0.2673553973},
{"learn":[3.542752124],"iteration":685,"passed_time":0.5819750075,"remaining_time":0.2663850618},
{"learn":[3.541334315],"iteration":686,"passed_time":0.5825757251,"remaining_time":0.2654238748},
{"learn":[3.540208266],"iteration":687,"passed_time":0.5831599693,"remaining_time":0.2644562651},
{"learn":[3.537730983],"iteration":688,"passed_time":0.5837726817,"remaining_time":0.2635026183},
{"learn":[3.53419867],"iteration":689,"passed_time":0.5843707642,"remaining_time":0.2625433868},
{"learn":[3.532628335],"iteration":690,"passed_time":0.5849395467,"remaining_time":0.2615720983},
{"learn":[3.532204987],"iteration":691,"passed_time":0.5857854861,"remaining_time":0.260725332},
{"learn":[3.530618147],"iteration":692,"passed_time":0.5865301081,"remaining_time":0.2598336843},
{"learn":[3.528909306],"iteration":693,"passed_time":0.5872496689,"remaining_time":0.2589314102},
{"learn":[3.526700678],"iteration":694,"passed_time":0.5880080208,"remaining_time":0.2580466854},
{"learn":[3.526439574],"iteration":695,"passed_time":0.5887528533,"remaining_time":0.2571564187},
{"learn":[3.525784216],"iteration":696,"passed_time":0.5893917191,"remaining_time":0.2562205034},
{"learn":[3.524112693],"iteration":697,"passed_time":0.5900586623,"remaining_time":0.2552975874},
{"learn":[3.522813541],"iteration":698,"passed_time":0.5906355515,"remaining_time":0.2543366252},
{"learn":[3.519148203],"iteration":699,"passed_time":0.5912265495,"remaining_time":0.2533828069},
{"learn":[3.517236747],"iteration":700,"passed_time":0.5919356437,"remaining_time":0.2524803958},
{"learn":[3.515603888],"iteration":701,"passed_time":0.5925681967,"remaining_time":0.2515460436},
{"learn":[3.51263524],"iteration":702,"passed_time":0.5931892661,"remaining_time":0.2506076985},
{"learn":[3.51123442],"iteration":703,"passed_time":0.5937790316,"remaining_time":0.2496570928},
{"learn":[3.50828027],"iteration":704,"passed_time":0.5943628149,"remaining_time":0.2487050076},
{"learn":[3.508265537],"iteration":705,"passed_time":0.5947321197,"remaining_time":0.2476646504},
{"learn":[3.506774876],"iteration":706,"passed_time":0.5953297713,"remaining_time":0.2467208246},
{"learn":[3.50552068],"iteration":707,"passed_time":0.5958906678,"remaining_time":0.2457628178},
{"learn":[3.501973993],"iteration":708,"passed_time":0.596484732,"remaining_time":0.2448195445},
{"learn":[3.498880354],"iteration":709,"passed_time":0.5970666014,"remaining_time":0.2438722738},
{"learn":[3.497370959],"iteration":710,"passed_time":0.5976487112,"remaining_time":0.2429261287},
{"learn":[3.496050455],"iteration":711,"passed_time":0.5982252697,"remaining_time":0.2419787608},
{"learn":[3.495630067],"iteration":712,"passed_time":0.5987908658,"remaining_time":0.2410280203},
{"learn":[3.49550669],"iteration":713,"passed_time":0.5993548986,"remaining_time":0.2400777325},
{"learn":[3.493652375],"iteration":714,"passed_time":0.599937249,"remaining_time":0.2391358265},
{"learn":[3.491915684],"iteration":715,"passed_time":0.6007528512,"remaining_time":0.2382874438},
{"learn":[3.490303956],"iteration":716,"passed_time":0.6014728228,"remaining_time":0.237401407},
{"learn":[3.488363853],"iteration":717,"passed_time":0.6021415995,"remaining_time":0.2364957257},
{"learn":[3.485483936],"iteration":718,"passed_time":0.6028027008,"remaining_time":0.2355877036},
{"learn":[3.483763466],"iteration":719,"passed_time":0.6035564918,"remaining_time":0.2347164135},
{"learn":[3.481642352],"iteration":720,"passed_time":0.6041657571,"remaining_time":0.2337895232},
{"learn":[3.479826119],"iteration":721,"passed_time":0.6047594907,"remaining_time":0.2328575324},
{"learn":[3.478588728],"iteration":722,"passed_time":0.605357954,"remaining_time":0.2319282894},
{"learn":[3.475390887],"iteration":723,"passed_time":0.6059641731,"remaining_time":0.2310029168},
{"learn":[3.472636852],"iteration":724,"passed_time":0.6065642596,"remaining_time":0.2300760985},
{"learn":[3.47061883],"iteration":725,"passed_time":0.6071932651,"remaining_time":0.2291610945},
{"learn":[3.46953149],"iteration":726,"passed_time":0.6077686812,"remaining_time":0.2282267537},
{"learn":[3.467217162],"iteration":727,"passed_time":0.608360551,"remaining_time":0.2272995465},
{"learn":[3.465686216],"iteration":728,"passed_time":0.6089281211,"remaining_time":0.2263642261},
{"learn":[3.462631216],"iteration":729,"passed_time":0.6095023849,"remaining_time":0.2254323889},
{"learn":[3.461451053],"iteration":730,"passed_time":0.6100730012,"remaining_time":0.2245001879},
{"learn":[3.458950469],"iteration":731,"passed_time":0.610650672,"remaining_time":0.2235715575},
{"learn":[3.458072145],"iteration":732,"passed_time":0.6112287736,"remaining_time":0.2226440417},
{"learn":[3.454364268],"iteration":733,"passed_time":0.6118195712,"remaining_time":0.2217220789},
{"learn":[3.453243406],"iteration":734,"passed_time":0.6123996569,"remaining_time":0.2207971552},
{"learn":[3.453017963],"iteration":735,"passed_time":0.6129716661,"remaining_time":0.2198702715},
{"learn":[3.45201581],"iteration":736,"passed_time":0.6135305584,"remaining_time":0.2189396701},
{"learn":[3.449510107],"iteration":737,"passed_time":0.6141220675,"remaining_time":0.2180216554},
{"learn":[3.447189189],"iteration":738,"passed_time":0.6147078348,"remaining_time":0.2171024964},
{"learn":[3.446423605],"iteration":739,"passed_time":0.6152965283,"remaining_time":0.2161852667},
{"learn":[3.445531987],"iteration":740,"passed_time":0.6160205282,"remaining_time":0.215316217},
{"learn":[3.445328199],"iteration":741,"passed_time":0.6166683022,"remaining_time":0.2144210539},
{"learn":[3.443327544],"iteration":742,"passed_time":0.6173802371,"remaining_time":0.2135487496},
{"learn":[3.441475798],"iteration":743,"passed_time":0.6180813201,"remaining_time":0.2126731424},
{"learn":[3.439046501],"iteration":744,"passed_time":0.6187282227,"remaining_time":0.2117794588},
{"learn":[3.435899469],"iteration":745,"passed_time":0.6193308244,"remaining_time":0.2108713531},
{"learn":[3.433988352],"iteration":746,"passed_time":0.6199115915,"remaining_time":0.2099566702},
{"learn":[3.433413263],"iteration":747,"passed_time":0.6204753638,"remaining_time":0.2090371547},
{"learn":[3.429944699],"iteration":748,"passed_time":0.6211610573,"remaining_time":0.2081594464},
{"learn":[3.429291634],"iteration":749,"passed_time":0.6217427963,"remaining_time":0.2072475988},
{"learn":[3.429175603],"iteration":750,"passed_time":0.6222990834,"remaining_time":0.2063281914},
{"learn":[3.428780323],"iteration":751,"passed_time":0.6228587473,"remaining_time":0.2054108635},
{"learn":[3.423893341],"iteration":752,"passed_time":0.6234527715,"remaining_time":0.2045057564},
{"learn":[3.421024316],"iteration":753,"passed_time":0.6240478879,"remaining_time":0.2036018308},
{"learn":[3.420969872],"iteration":754,"passed_time":0.6246123216,"remaining_time":0.2026887666},
{"learn":[3.419544785],"iteration":755,"passed_time":0.6251846615,"remaining_time":0.2017791765},
{"learn":[3.417057977],"iteration":756,"passed_time":0.6257655288,"remaining_time":0.2008732147},
{"learn":[3.415160245],"iteration":757,"passed_time":0.626350294,"remaining_time":0.1999693551},
{"learn":[3.412854597],"iteration":758,"passed_time":0.6269364421,"remaining_time":0.1990667754},
{"learn":[3.410926347],"iteration":759,"passed_time":0.6275269792,"remaining_time":0.1981664145},
{"learn":[3.408963843],"iteration":760,"passed_time":0.6280990084,"remaining_time":0.1972610552},
{"learn":[3.407629634],"iteration":761,"passed_time":0.6286549447,"remaining_time":0.1963515444},
{"learn":[3.404384724],"iteration":762,"passed_time":0.6292400707,"remaining_time":0.1954520272},
{"learn":[3.403041656],"iteration":763,"passed_time":0.6298144247,"remaining_time":0.1945500055},
{"learn":[3.401101731],"iteration":764,"passed_time":0.6303971157,"remaining_time":0.1936514016},
{"learn":[3.400890668],"iteration":765,"passed_time":0.6312083517,"remaining_time":0.192823439},
{"learn":[3.399289941],"iteration":766,"passed_time":0.6318650943,"remaining_time":0.191948588},
{"learn":[3.399202366],"iteration":767,"passed_time":0.6324966352,"remaining_time":0.1910666919},
{"learn":[3.397447845],"iteration":768,"passed_time":0.6331755627,"remaining_time":0.1901996814},
{"learn":[3.394655341],"iteration":769,"passed_time":0.633831784,"remaining_time":0.189326377},
{"learn":[3.393228229],"iteration":770,"passed_time":0.6344867229,"remaining_time":0.1884532549},
{"learn":[3.389691197],"iteration":771,"passed_time":0.6351665525,"remaining_time":0.1875880492},
{"learn":[3.389626772],"iteration":772,"passed_time":0.6359820513,"remaining_time":0.1867631638},
{"learn":[3.388480222],"iteration":773,"passed_time":0.6367344269,"remaining_time":0.1859198714},
{"learn":[3.388215066],"iteration":774,"passed_time":0.6374694696,"remaining_time":0.1850717815},
{"learn":[3.386324358],"iteration":775,"passed_time":0.6381373645,"remaining_time":0.1842046001},
{"learn":[3.383913061],"iteration":776,"passed_time":0.6387333728,"remaining_time":0.1833173},
{"learn":[3.382839768],"iteration":777,"passed_time":0.6393641421,"remaining_time":0.1824406678},
{"learn":[3.381961844],"iteration":778,"passed_time":0.6399390271,"remaining_time":0.1815488126},
{"learn":[3.381521703],"iteration":779,"passed_time":0.6405083608,"remaining_time":0.1806562043},
{"learn":[3.380918963],"iteration":780,"passed_time":0.6410880858,"remaining_time":0.1797673378},
{"learn":[3.377139006],"iteration":781,"passed_time":0.6416781519,"remaining_time":0.1788821446},
{"learn":[3.376004372],"iteration":782,"passed_time":0.6422366935,"remaining_time":0.1779889687},
{"learn":[3.373826468],"iteration":783,"passed_time":0.6428048348,"remaining_time":0.1770992912},
{"learn":[3.373546786],"iteration":784,"passed_time":0.6433658315,"remaining_time":0.1762084761},
{"learn":[3.372109181],"iteration":785,"passed_time":0.6439501458,"remaining_time":0.1753248489},
{"learn":[3.370764924],"iteration":786,"passed_time":0.6445540023,"remaining_time":0.1744472713},
{"learn":[3.367833107],"iteration":787,"passed_time":0.6451663539,"remaining_time":0.1735726739},
{"learn":[3.36450404],"iteration":788,"passed_time":0.6458878186,"remaining_time":0.1727279211},
{"learn":[3.361794558],"iteration":789,"passed_time":0.6466017281,"remaining_time":0.171881472},
{"learn":[3.356880529],"iteration":790,"passed_time":0.6472207233,"remaining_time":0.1710102796},
{"learn":[3.353843509],"iteration":791,"passed_time":0.6478102883,"remaining_time":0.1701319949},
{"learn":[3.353640253],"iteration":792,"passed_time":0.6483515146,"remaining_time":0.1692418203},
{"learn":[3.353055088],"iteration":793,"passed_time":0.6489248914,"remaining_time":0.168360866},
{"learn":[3.351415617],"iteration":794,"passed_time":0.6494996763,"remaining_time":0.1674810486},
{"learn":[3.349169061],"iteration":795,"passed_time":0.6500869367,"remaining_time":0.1666051948},
{"learn":[3.346211014],"iteration":796,"passed_time":0.6506665714,"remaining_time":0.165728123},
{"learn":[3.344560452],"iteration":797,"passed_time":0.6512319671,"remaining_time":0.1648481922},
{"learn":[3.344445461],"iteration":798,"passed_time":0.6517932644,"remaining_time":0.1639680177},
{"learn":[3.342608898],"iteration":799,"passed_time":0.6523721176,"remaining_time":0.1630930294},
{"learn":[3.339572899],"iteration":800,"passed_time":0.6530011333,"remaining_time":0.1622312428},
{"learn":[3.339309302],"iteration":801,"passed_time":0.6535893957,"remaining_time":0.1613599755},
{"learn":[3.33698088],"iteration":802,"passed_time":0.6541562343,"remaining_time":0.1604841571},
{"learn":[3.334746342],"iteration":803,"passed_time":0.6547474427,"remaining_time":0.1596150482},
{"learn":[3.332048511],"iteration":804,"passed_time":0.65531855,"remaining_time":0.1587417606},
{"learn":[3.331932544],"iteration":805,"passed_time":0.6558797672,"remaining_time":0.1578668422},
{"learn":[3.330541133],"iteration":806,"passed_time":0.6564429483,"remaining_time":0.156993171},
{"learn":[3.329124989],"iteration":807,"passed_time":0.6570183845,"remaining_time":0.1561231805},
{"learn":[3.32583918],"iteration":808,"passed_time":0.6575742707,"remaining_time":0.1552493025},
{"learn":[3.325287299],"iteration":809,"passed_time":0.6581367304,"remaining_time":0.1543777516},
{"learn":[3.322745162],"iteration":810,"passed_time":0.6586982882,"remaining_time":0.1535067527},
{"learn":[3.319733662],"iteration":811,"passed_time":0.6592843862,"remaining_time":0.1526421978},
{"learn":[3.318080007],"iteration":812,"passed_time":0.659844471,"remaining_time":0.1517723445},
{"learn":[3.317179538],"iteration":813,"passed_time":0.6604187849,"remaining_time":0.1509065037},
{"learn":[3.315685949],"iteration":814,"passed_time":0.6610927424,"remaining_time":0.1500639967},
{"learn":[3.314944576],"iteration":815,"passed_time":0.6617229907,"remaining_time":0.1492120469},
{"learn":[3.312369052],"iteration":816,"passed_time":0.6623195901,"remaining_time":0.1483531028},
{"learn":[3.312321621],"iteration":817,"passed_time":0.6627528457,"remaining_time":0.1474584571},
{"learn":[3.309465776],"iteration":818,"passed_time":0.6633384326,"remaining_time":0.1465986035},
{"learn":[3.308307377],"iteration":819,"passed_time":0.663937467,"remaining_time":0.1457423708},
{"learn":[3.308076804],"iteration":820,"passed_time":0.664473182,"remaining_time":0.1448729593},
{"learn":[3.305643326],"iteration":821,"passed_time":0.665052897,"remaining_time":0.1440138877},
{"learn":[3.304154814],"iteration":822,"passed_time":0.6656250364,"remaining_time":0.1431538657},
{"learn":[3.303076321],"iteration":823,"passed_time":0.6661902317,"remaining_time":0.1422930592},
{"learn":[3.301746372],"iteration":824,"passed_time":0.666774526,"remaining_time":0.1414370207},
{"learn":[3.301345455],"iteration":825,"passed_time":0.6673335787,"remaining_time":0.1405763229},
{"learn":[3.299181039],"iteration":826,"passed_time":0.6679117404,"remaining_time":0.139720352},
{"learn":[3.297989357],"iteration":827,"passed_time":0.6684750518,"remaining_time":0.1388619673},
{"learn":[3.294775182],"iteration":828,"passed_time":0.669069096,"remaining_time":0.1380106338},
{"learn":[3.293840636],"iteration":829,"passed_time":0.6696397324,"remaining_time":0.1371551259},
{"learn":[3.289279397],"iteration":830,"passed_time":0.6702223332,"remaining_time":0.1363027368},
{"learn":[3.286204979],"iteration":831,"passed_time":0.6707958355,"remaining_time":0.1354491591},
{"learn":[3.284833593],"iteration":832,"passed_time":0.6713663115,"remaining_time":0.1345956471},
{"learn":[3.283519914],"iteration":833,"passed_time":0.6719314867,"remaining_time":0.1337417588},
{"learn":[3.282853026],"iteration":834,"passed_time":0.6724967622,"remaining_time":0.1328885817},
{"learn":[3.281944673],"iteration":835,"passed_time":0.6730628492,"remaining_time":0.1320362527},
{"learn":[3.279764865],"iteration":836,"passed_time":0.673641021,"remaining_time":0.1311869611},
{"learn":[3.277468839],"iteration":837,"passed_time":0.6742101744,"remaining_time":0.1303365731},
{"learn":[3.277124974],"iteration":838,"passed_time":0.6747710007,"remaining_time":0.1294852576},
{"learn":[3.275636037],"iteration":839,"passed_time":0.6753313861,"remaining_time":0.1286345497},
{"learn":[3.274413635],"iteration":840,"passed_time":0.6759104998,"remaining_time":0.1277880731},
{"learn":[3.272636087],"iteration":841,"passed_time":0.6765971934,"remaining_time":0.1269624187},
{"learn":[3.269644466],"iteration":842,"passed_time":0.6772013483,"remaining_time":0.126121722},
{"learn":[3.26852083],"iteration":843,"passed_time":0.6777778867,"remaining_time":0.1252764814},
{"learn":[3.267820927],"iteration":844,"passed_time":0.6783843163,"remaining_time":0.1244373598},
{"learn":[3.267331099],"iteration":845,"passed_time":0.6789671576,"remaining_time":0.1235944944},
{"learn":[3.267231014],"iteration":846,"passed_time":0.679519236,"remaining_time":0.1227466861},
{"learn":[3.267158695],"iteration":847,"passed_time":0.6800657431,"remaining_time":0.1218985766},
{"learn":[3.264718705],"iteration":848,"passed_time":0.680649336,"remaining_time":0.1210577735},
{"learn":[3.261678512],"iteration":849,"passed_time":0.6812400534,"remaining_time":0.1202188329},
{"learn":[3.261368381],"iteration":850,"passed_time":0.6818069822,"remaining_time":0.1193763106},
{"learn":[3.260128799],"iteration":851,"passed_time":0.6823705341,"remaining_time":0.1185338486},
{"learn":[3.258972952],"iteration":852,"passed_time":0.6829725346,"remaining_time":0.1176986666},
{"learn":[3.258724846],"iteration":853,"passed_time":0.6835292926,"remaining_time":0.1168562959},
{"learn":[3.25686724],"iteration":854,"passed_time":0.6840992275,"remaining_time":0.1160168281},
{"learn":[3.255750259],"iteration":855,"passed_time":0.6846715974,"remaining_time":0.1151783996},
{"learn":[3.254915866],"iteration":856,"passed_time":0.685241833,"remaining_time":0.1143402358},
{"learn":[3.254348625],"iteration":857,"passed_time":0.6858074892,"remaining_time":0.1135019388},
{"learn":[3.253408514],"iteration":858,"passed_time":0.6863642472,"remaining_time":0.1126628159},
{"learn":[3.253291714],"iteration":859,"passed_time":0.6868963548,"remaining_time":0.1118203368},
{"learn":[3.250186342],"iteration":860,"passed_time":0.68749577,"remaining_time":0.1109894449},
{"learn":[3.249141318],"iteration":861,"passed_time":0.6880654745,"remaining_time":0.1101543335},
{"learn":[3.246300388],"iteration":862,"passed_time":0.6886555205,"remaining_time":0.1093230664},
{"learn":[3.245205135],"iteration":863,"passed_time":0.6892380312,"remaining_time":0.1084911716},
{"learn":[3.244403535],"iteration":864,"passed_time":0.6898066835,"remaining_time":0.1076576905},
{"learn":[3.244211781],"iteration":865,"passed_time":0.6903723597,"remaining_time":0.1068243605},
{"learn":[3.242286347],"iteration":866,"passed_time":0.6909434571,"remaining_time":0.1059924796},
{"learn":[3.239606746],"iteration":867,"passed_time":0.6915479724,"remaining_time":0.1051662815},
{"learn":[3.236773361],"iteration":868,"passed_time":0.6921359142,"remaining_time":0.1043380952},
{"learn":[3.234552446],"iteration":869,"passed_time":0.6927308123,"remaining_time":0.1035115007},
{"learn":[3.233724647],"iteration":870,"passed_time":0.6933211389,"remaining_time":0.1026847611},
{"learn":[3.230851485],"iteration":871,"passed_time":0.6939144115,"remaining_time":0.1018589962},
{"learn":[3.227728941],"iteration":872,"passed_time":0.6945375883,"remaining_time":0.1010381142},
{"learn":[3.225787575],"iteration":873,"passed_time":0.6951179546,"remaining_time":0.1002115129},
{"learn":[3.222797487],"iteration":874,"passed_time":0.695709644,"remaining_time":0.09938709199},
{"learn":[3.22137014],"iteration":875,"passed_time":0.696266883,"remaining_time":0.0985583259},
{"learn":[3.219701963],"iteration":876,"passed_time":0.6968448643,"remaining_time":0.09773308816},
{"learn":[3.21783327],"iteration":877,"passed_time":0.6974471955,"remaining_time":0.0969117971},
{"learn":[3.217713355],"iteration":878,"passed_time":0.6980126713,"remaining_time":0.09608593087},
{"learn":[3.217666091],"iteration":879,"passed_time":0.6985329748,"remaining_time":0.09525449657},
{"learn":[3.214962005],"iteration":880,"passed_time":0.6991319892,"remaining_time":0.09443440036},
{"learn":[3.214081828],"iteration":881,"passed_time":0.6996907112,"remaining_time":0.09360941488},
{"learn":[3.213358337],"iteration":882,"passed_time":0.7002799556,"remaining_time":0.0927890768},
{"learn":[3.210850401],"iteration":883,"passed_time":0.7008612538,"remaining_time":0.09196821883},
{"learn":[3.207810328],"iteration":884,"passed_time":0.7014321307,"remaining_time":0.09114654805},
{"learn":[3.204935073],"iteration":885,"passed_time":0.7020029174,"remaining_time":0.09032543181},
{"learn":[3.20280198],"iteration":886,"passed_time":0.7025828427,"remaining_time":0.08950604423},
{"learn":[3.200663495],"iteration":887,"passed_time":0.703181807,"remaining_time":0.08868959728},
{"learn":[3.197301669],"iteration":888,"passed_time":0.7037481847,"remaining_time":0.08786957086},
{"learn":[3.195666943],"iteration":889,"passed_time":0.704314412,"remaining_time":0.08705009587},
{"learn":[3.193886506],"iteration":890,"passed_time":0.7048889664,"remaining_time":0.08623220801},
{"learn":[3.190601248],"iteration":891,"passed_time":0.7054697034,"remaining_time":0.08541561432},
{"learn":[3.188983797],"iteration":892,"passed_time":0.70604041,"remaining_time":0.08459834699},
{"learn":[3.187365749],"iteration":893,"passed_time":0.7066239627,"remaining_time":0.08378315442},
{"learn":[3.186160771],"iteration":894,"passed_time":0.707249416,"remaining_time":0.08297339518},
{"learn":[3.185358981],"iteration":895,"passed_time":0.7078393118,"remaining_time":0.08215992012},
{"learn":[3.183832164],"iteration":896,"passed_time":0.7084295582,"remaining_time":0.08134698383},
{"learn":[3.183106966],"iteration":897,"passed_time":0.7090056658,"remaining_time":0.08053293754},
{"learn":[3.182838152],"iteration":898,"passed_time":0.709563015,"remaining_time":0.07971731314},
{"learn":[3.180835453],"iteration":899,"passed_time":0.7101553457,"remaining_time":0.07890614952},
{"learn":[3.179957348],"iteration":900,"passed_time":0.7107092679,"remaining_time":0.07809125142},
{"learn":[3.179752966],"iteration":901,"passed_time":0.7112662664,"remaining_time":0.0772772662},
{"learn":[3.178851983],"iteration":902,"passed_time":0.7118425644,"remaining_time":0.07646592331},
{"learn":[3.176748586],"iteration":903,"passed_time":0.7124075893,"remaining_time":0.07565390329},
{"learn":[3.172960988],"iteration":904,"passed_time":0.7129981263,"remaining_time":0.07484510719},
{"learn":[3.172794225],"iteration":905,"passed_time":0.713537599,"remaining_time":0.07403149482},
{"learn":[3.169996507],"iteration":906,"passed_time":0.7141206808,"remaining_time":0.07322295845},
{"learn":[3.16813015],"iteration":907,"passed_time":0.7146903953,"remaining_time":0.07241356428},
{"learn":[3.166920871],"iteration":908,"passed_time":0.7152528349,"remaining_time":0.07160396918},
{"learn":[3.16531606],"iteration":909,"passed_time":0.7158155652,"remaining_time":0.07079494601},
{"learn":[3.162035247],"iteration":910,"passed_time":0.7163940476,"remaining_time":0.06998800245},
{"learn":[3.16189467],"iteration":911,"passed_time":0.7169291613,"remaining_time":0.06917737522},
{"learn":[3.161008416],"iteration":912,"passed_time":0.7174942664,"remaining_time":0.0683702094},
{"learn":[3.160560787],"iteration":913,"passed_time":0.7180480183,"remaining_time":0.067562505},
{"learn":[3.160416261],"iteration":914,"passed_time":0.7185951366,"remaining_time":0.06675473946},
{"learn":[3.15844291],"iteration":915,"passed_time":0.7191653922,"remaining_time":0.06594966479},
{"learn":[3.155040501],"iteration":916,"passed_time":0.7197501775,"remaining_time":0.06514641737},
{"learn":[3.154937548],"iteration":917,"passed_time":0.7203041799,"remaining_time":0.06434089624},
{"learn":[3.153721161],"iteration":918,"passed_time":0.7208772011,"remaining_time":0.06353759879},
{"learn":[3.153170511],"iteration":919,"passed_time":0.7214581385,"remaining_time":0.06273549031},
{"learn":[3.153113601],"iteration":920,"passed_time":0.7220144556,"remaining_time":0.06193175027},
{"learn":[3.150607379],"iteration":921,"passed_time":0.7226003432,"remaining_time":0.06113104856},
{"learn":[3.148408359],"iteration":922,"passed_time":0.7231985459,"remaining_time":0.06033183969},
{"learn":[3.147495728],"iteration":923,"passed_time":0.7237663565,"remaining_time":0.05953056612},
{"learn":[3.146946235],"iteration":924,"passed_time":0.7243229642,"remaining_time":0.05872888899},
{"learn":[3.14472738],"iteration":925,"passed_time":0.7249032403,"remaining_time":0.05792963259},
{"learn":[3.144469477],"iteration":926,"passed_time":0.7254898694,"remaining_time":0.05713134894},
{"learn":[3.142975516],"iteration":927,"passed_time":0.7260527599,"remaining_time":0.05633167965},
{"learn":[3.14079113],"iteration":928,"passed_time":0.7266297092,"remaining_time":0.05553359457},
{"learn":[3.138173032],"iteration":929,"passed_time":0.7272001852,"remaining_time":0.05473549781},
{"learn":[3.136352813],"iteration":930,"passed_time":0.7277799503,"remaining_time":0.05393857848},
{"learn":[3.133735004],"iteration":931,"passed_time":0.7283476506,"remaining_time":0.0531412449},
{"learn":[3.1319496],"iteration":932,"passed_time":0.7289343599,"remaining_time":0.05234576861},
{"learn":[3.129865343],"iteration":933,"passed_time":0.729515127,"remaining_time":0.05155031946},
{"learn":[3.129830206],"iteration":934,"passed_time":0.7299409072,"remaining_time":0.05074455505},
{"learn":[3.126676562],"iteration":935,"passed_time":0.7305343502,"remaining_time":0.04995106668},
{"learn":[3.12645665],"iteration":936,"passed_time":0.7310877113,"remaining_time":0.04915531037},
{"learn":[3.126378007],"iteration":937,"passed_time":0.7316249594,"remaining_time":0.04835900585},
{"learn":[3.124621914],"iteration":938,"passed_time":0.7321988324,"remaining_time":0.04756563235},
{"learn":[3.123379018],"iteration":939,"passed_time":0.7327773148,"remaining_time":0.0467730201},
{"learn":[3.123332451],"iteration":940,"passed_time":0.7333224591,"remaining_time":0.04597877268},
{"learn":[3.122432444],"iteration":941,"passed_time":0.7338896084,"remaining_time":0.04518640901},
{"learn":[3.121889006],"iteration":942,"passed_time":0.7344450537,"remaining_time":0.04439381555},
{"learn":[3.121070914],"iteration":943,"passed_time":0.7350607124,"remaining_time":0.0436052965},
{"learn":[3.118444705],"iteration":944,"passed_time":0.7356516402,"remaining_time":0.04281570393},
{"learn":[3.116820458],"iteration":945,"passed_time":0.7362395319,"remaining_time":0.04202635806},
{"learn":[3.114971041],"iteration":946,"passed_time":0.7368171325,"remaining_time":0.04123686169},
{"learn":[3.114685138],"iteration":947,"passed_time":0.7374036313,"remaining_time":0.04044830045},
{"learn":[3.113399363],"iteration":948,"passed_time":0.7379914628,"remaining_time":0.03966023667},
{"learn":[3.110575399],"iteration":949,"passed_time":0.7385719393,"remaining_time":0.03887220733},
{"learn":[3.110466553],"iteration":950,"passed_time":0.7391093578,"remaining_time":0.03808239593},
{"learn":[3.108691641],"iteration":951,"passed_time":0.739701929,"remaining_time":0.03729589558},
{"learn":[3.107898017],"iteration":952,"passed_time":0.7402482156,"remaining_time":0.03650751955},
{"learn":[3.105551729],"iteration":953,"passed_time":0.7408440034,"remaining_time":0.0357220379},
{"learn":[3.104824945],"iteration":954,"passed_time":0.7414234978,"remaining_time":0.03493618576},
{"learn":[3.103186704],"iteration":955,"passed_time":0.7420180932,"remaining_time":0.03415146036},
{"learn":[3.102330655],"iteration":956,"passed_time":0.74258892,"remaining_time":0.03336606432},
{"learn":[3.102291298],"iteration":957,"passed_time":0.7431366996,"remaining_time":0.03258010583},
{"learn":[3.100363529],"iteration":958,"passed_time":0.7437157732,"remaining_time":0.03179598196},
{"learn":[3.097871596],"iteration":959,"passed_time":0.7443187557,"remaining_time":0.03101328149},
{"learn":[3.097372213],"iteration":960,"passed_time":0.7449009958,"remaining_time":0.03023011325},
{"learn":[3.095981813],"iteration":961,"passed_time":0.745463696,"remaining_time":0.0294465909},
{"learn":[3.095347452],"iteration":962,"passed_time":0.7460485715,"remaining_time":0.02866437917},
{"learn":[3.094728409],"iteration":963,"passed_time":0.7466112415,"remaining_time":0.02788174761},
{"learn":[3.094118537],"iteration":964,"passed_time":0.747190255,"remaining_time":0.02710016469},
{"learn":[3.093793695],"iteration":965,"passed_time":0.7477392973,"remaining_time":0.02631794628},
{"learn":[3.092581602],"iteration":966,"passed_time":0.7483153447,"remaining_time":0.02553713172},
{"learn":[3.091694202],"iteration":967,"passed_time":0.7488963122,"remaining_time":0.02475690288},
{"learn":[3.090298312],"iteration":968,"passed_time":0.7495066998,"remaining_time":0.02397802652},
{"learn":[3.090020107],"iteration":969,"passed_time":0.7500559926,"remaining_time":0.02319760802},
{"learn":[3.088949869],"iteration":970,"passed_time":0.7506195445,"remaining_time":0.02241809144},
{"learn":[3.086700204],"iteration":971,"passed_time":0.7512033378,"remaining_time":0.02163960232},
{"learn":[3.086584317],"iteration":972,"passed_time":0.7517563882,"remaining_time":0.02086066031},
{"learn":[3.084850742],"iteration":973,"passed_time":0.7523353917,"remaining_time":0.02008287493},
{"learn":[3.084239948],"iteration":974,"passed_time":0.7529497574,"remaining_time":0.01930640404},
{"learn":[3.082561673],"iteration":975,"passed_time":0.7535445532,"remaining_time":0.01852978409},
{"learn":[3.07991814],"iteration":976,"passed_time":0.754123737,"remaining_time":0.01775316883},
{"learn":[3.079350277],"iteration":977,"passed_time":0.7546854351,"remaining_time":0.01697656398},
{"learn":[3.077637462],"iteration":978,"passed_time":0.7552687073,"remaining_time":0.01620086093},
{"learn":[3.076733301],"iteration":979,"passed_time":0.7558226796,"remaining_time":0.01542495265},
{"learn":[3.07594065],"iteration":980,"passed_time":0.7563836362,"remaining_time":0.0146496321},
{"learn":[3.072594655],"iteration":981,"passed_time":0.7569811175,"remaining_time":0.01387541763},
{"learn":[3.071977674],"iteration":982,"passed_time":0.7575462025,"remaining_time":0.01310100248},
{"learn":[3.069532634],"iteration":983,"passed_time":0.7581224203,"remaining_time":0.01232719383},
{"learn":[3.068870784],"iteration":984,"passed_time":0.7586791482,"remaining_time":0.01155348957},
{"learn":[3.068801463],"iteration":985,"passed_time":0.7592296334,"remaining_time":0.01078013678},
{"learn":[3.067433249],"iteration":986,"passed_time":0.759801322,"remaining_time":0.01000751488},
{"learn":[3.065611456],"iteration":987,"passed_time":0.7603919191,"remaining_time":0.009235529382},
{"learn":[3.063039162],"iteration":988,"passed_time":0.7609627259,"remaining_time":0.008463690581},
{"learn":[3.06177873],"iteration":989,"passed_time":0.7615536236,"remaining_time":0.007692460845},
{"learn":[3.061689148],"iteration":990,"passed_time":0.7620886172,"remaining_time":0.006921087341},
{"learn":[3.058984039],"iteration":991,"passed_time":0.7626713282,"remaining_time":0.006150575228},
{"learn":[3.057492984],"iteration":992,"passed_time":0.7632481673,"remaining_time":0.005380399971},
{"learn":[3.057290731],"iteration":993,"passed_time":0.7638385291,"remaining_time":0.004610695347},
{"learn":[3.056068348],"iteration":994,"passed_time":0.764420649,"remaining_time":0.003841309794},
{"learn":[3.054987307],"iteration":995,"passed_time":0.7649831687,"remaining_time":0.003072221561},
{"learn":[3.054200234],"iteration":996,"passed_time":0.7655484341,"remaining_time":0.00230355597},
{"learn":[3.052732869],"iteration":997,"passed_time":0.7661287703,"remaining_time":0.001535328197},
{"learn":[3.051787862],"iteration":998,"passed_time":0.7667037857,"remaining_time":0.0007674712569},
{"learn":[3.051366222],"iteration":999,"passed_time":0.7672544612,"remaining_time":0}
]}